{
  "total": 318,
  "repos": [
    {
      "owner": "HoangDangers",
      "repo": "hd123",
      "date": "2025-08-03T00:13:31Z"
    },
    {
      "owner": "VVVpa3ck",
      "repo": "1",
      "date": "2025-08-01T04:24:32Z"
    },
    {
      "owner": "yoon507342-cloud",
      "repo": "lab-website-template",
      "date": "2025-07-31T13:26:42Z"
    },
    {
      "owner": "piravich8373-cmd",
      "repo": "lab-website-template",
      "date": "2025-07-26T10:45:18Z"
    },
    {
      "owner": "csun-carelab",
      "repo": "csun-carelab.github.io",
      "date": "2025-07-24T00:38:48Z"
    },
    {
      "owner": "iSQARE-Lab",
      "repo": "lab-website",
      "date": "2025-07-23T14:49:55Z"
    },
    {
      "owner": "aaaazan",
      "repo": "lab-website-template",
      "date": "2025-07-23T12:36:15Z"
    },
    {
      "owner": "flyingstarme",
      "repo": "Mylab",
      "date": "2025-07-21T10:46:17Z"
    },
    {
      "owner": "Gu-Weihua",
      "repo": "Gu-Weihua",
      "date": "2025-07-16T11:10:38Z"
    },
    {
      "owner": "xiaohua-luo",
      "repo": "lab",
      "date": "2025-07-14T20:28:31Z"
    },
    {
      "owner": "primal-lab",
      "repo": "primal-lab-website",
      "date": "2025-07-09T17:24:02Z"
    },
    {
      "owner": "Smart-Transit-Lab",
      "repo": "lab-website",
      "date": "2025-07-08T14:15:58Z"
    },
    {
      "owner": "xkzhaohit",
      "repo": "smart-transit.github.io",
      "date": "2025-07-08T13:47:45Z"
    },
    {
      "owner": "arani89",
      "repo": "wise-lab-webpage",
      "date": "2025-07-07T09:41:53Z"
    },
    {
      "owner": "karlgrieshop",
      "repo": "karlgrieshop.github.io",
      "date": "2025-07-03T13:05:38Z"
    },
    {
      "owner": "AntonyVRGITHUB",
      "repo": "lab-website-template",
      "date": "2025-06-27T03:47:41Z"
    },
    {
      "owner": "IDImmune",
      "repo": "lab-website_V1",
      "date": "2025-06-26T11:05:25Z"
    },
    {
      "owner": "p4mars",
      "repo": "website",
      "date": "2025-06-24T07:54:29Z"
    },
    {
      "owner": "superqiang-cc",
      "repo": "superqiang-cc.github.io",
      "date": "2025-06-23T23:47:18Z"
    },
    {
      "owner": "MRdep",
      "repo": "lab-website-template",
      "date": "2025-06-21T13:22:16Z"
    },
    {
      "owner": "Zhou-ust",
      "repo": "lab-website-template",
      "date": "2025-06-17T05:23:07Z"
    },
    {
      "owner": "Stars1233",
      "repo": "lab-website-template",
      "date": "2025-06-16T07:38:52Z"
    },
    {
      "owner": "UAlbertaVISUAL",
      "repo": "visual-lab-website",
      "date": "2025-06-10T21:32:56Z"
    },
    {
      "owner": "MAVIlab-Mizzou",
      "repo": "MAVIlab-Mizzou.github.io",
      "date": "2025-06-05T22:34:55Z"
    },
    {
      "owner": "magnetic-gear",
      "repo": "zhaohang-lab-website",
      "date": "2025-06-03T13:35:42Z"
    },
    {
      "owner": "RSTiwari11",
      "repo": "lab-website-template",
      "date": "2025-05-28T07:12:50Z"
    },
    {
      "owner": "HRJ-xiaoliu",
      "repo": "digital_agriculture_team_web",
      "date": "2025-05-27T08:15:39Z"
    },
    {
      "owner": "JusticeJoe0128",
      "repo": "justicejoe0128",
      "date": "2025-05-26T13:15:29Z"
    },
    {
      "owner": "TiYooY",
      "repo": "lab-website-template",
      "date": "2025-05-22T18:42:42Z"
    },
    {
      "owner": "Furan2024",
      "repo": "Furan2024.github.io",
      "date": "2025-05-16T06:50:43Z"
    },
    {
      "owner": "poudellab",
      "repo": "poudellab",
      "date": "2025-05-15T04:43:41Z"
    },
    {
      "owner": "Tr33Bug",
      "repo": "lab-website-template-test",
      "date": "2025-05-14T14:52:05Z"
    },
    {
      "owner": "rkjcollab",
      "repo": "lab-website",
      "date": "2025-05-08T21:25:37Z"
    },
    {
      "owner": "Hamim-98-PT",
      "repo": "lab-website-template",
      "date": "2025-05-04T18:03:28Z"
    },
    {
      "owner": "AishwaryaManjunath2000",
      "repo": "aishwaryamanjunath2000.github.io",
      "date": "2025-05-03T04:12:33Z"
    },
    {
      "owner": "jade121213",
      "repo": "LabTemplate1",
      "date": "2025-04-25T20:38:03Z"
    },
    {
      "owner": "xRNAlab",
      "repo": "Research",
      "date": "2025-04-20T13:52:06Z"
    },
    {
      "owner": "dkim-unc",
      "repo": "heelsec-website",
      "date": "2025-04-17T20:17:12Z"
    },
    {
      "owner": "calsines",
      "repo": "lab-website-template",
      "date": "2025-04-14T08:35:27Z"
    },
    {
      "owner": "shammo-24",
      "repo": "lab-website-template",
      "date": "2025-04-04T19:33:42Z"
    },
    {
      "owner": "DrGLDavidson",
      "repo": "ACMEresearch",
      "date": "2025-04-04T09:42:20Z"
    },
    {
      "owner": "jonasns",
      "repo": "sondergaardlab",
      "date": "2025-04-02T13:48:28Z"
    },
    {
      "owner": "Penn-RAIL",
      "repo": "rail-lab-website",
      "date": "2025-04-01T17:38:35Z"
    },
    {
      "owner": "Pan-lab-SMART",
      "repo": "Pan-lab-website",
      "date": "2025-03-28T06:06:31Z"
    },
    {
      "owner": "marcouderzo",
      "repo": "STLAN-Team-IGFL",
      "date": "2025-03-24T13:48:38Z"
    },
    {
      "owner": "BerserkerVV",
      "repo": "lB",
      "date": "2025-03-22T12:51:50Z"
    },
    {
      "owner": "solid-li-lab2025",
      "repo": "web",
      "date": "2025-03-16T00:12:04Z"
    },
    {
      "owner": "sanjay7178",
      "repo": "lab-website-template",
      "date": "2025-03-15T14:13:19Z"
    },
    {
      "owner": "GleenDev",
      "repo": "lab-website-template",
      "date": "2025-03-14T03:06:23Z"
    },
    {
      "owner": "jung-gina",
      "repo": "lab-website-template",
      "date": "2025-03-13T07:48:58Z"
    },
    {
      "owner": "IRCASE",
      "repo": "AAS-template",
      "date": "2025-03-04T09:41:58Z"
    },
    {
      "owner": "hatelikeit",
      "repo": "Devansh-",
      "date": "2025-03-03T22:50:14Z"
    },
    {
      "owner": "dnslab-inha",
      "repo": "dnslab-inha.github.io",
      "date": "2025-03-01T07:11:00Z"
    },
    {
      "owner": "chenjing-pku",
      "repo": "chenjing-pku.github.io",
      "date": "2025-02-28T02:17:47Z"
    },
    {
      "owner": "ashwinashok",
      "repo": "lab-website-template",
      "date": "2025-02-27T05:50:33Z"
    },
    {
      "owner": "cjorda15",
      "repo": "somethingnew",
      "date": "2025-02-22T05:00:55Z"
    },
    {
      "owner": "Laurenz-fx",
      "repo": "State-Estimation-Lab-Website",
      "date": "2025-02-21T19:29:49Z"
    },
    {
      "owner": "NoethRin",
      "repo": "PKU_SHRC_CJLAB",
      "date": "2025-02-20T06:36:36Z"
    },
    {
      "owner": "cosinelab-iitism",
      "repo": "cosinelab-iitism.github.io",
      "date": "2025-02-16T18:26:32Z"
    },
    {
      "owner": "GlobalKnowledgeObservatory",
      "repo": "globalknowledgeobservatory.github.io",
      "date": "2025-02-15T13:11:16Z"
    },
    {
      "owner": "tejasrode",
      "repo": "home",
      "date": "2025-02-13T22:37:32Z"
    },
    {
      "owner": "gai3k",
      "repo": "gai3k.github.io",
      "date": "2025-02-13T21:56:59Z"
    },
    {
      "owner": "sunnygirlzyq",
      "repo": "lab-website-template.io",
      "date": "2025-02-06T01:57:06Z"
    },
    {
      "owner": "kaicalvin",
      "repo": "lab-website-template",
      "date": "2025-01-30T06:01:44Z"
    },
    {
      "owner": "zfg2013",
      "repo": "phd-website-template",
      "date": "2025-01-26T15:33:56Z"
    },
    {
      "owner": "muharif",
      "repo": "labtest",
      "date": "2025-01-09T12:12:39Z"
    },
    {
      "owner": "wilcoxkr",
      "repo": "predictive-ecology",
      "date": "2025-01-09T00:03:19Z"
    },
    {
      "owner": "MechSafety",
      "repo": "lab-website",
      "date": "2025-01-07T09:18:21Z"
    },
    {
      "owner": "Stellwagen",
      "repo": "stellwagen.github.io",
      "date": "2025-01-06T02:29:57Z"
    },
    {
      "owner": "Agentic-Intelligence-Lab",
      "repo": "Agentic-Intelligence-Lab.github.io",
      "date": "2025-01-02T17:35:28Z"
    },
    {
      "owner": "MatinGhanbari",
      "repo": "lab-website-template",
      "date": "2024-12-25T08:51:57Z"
    },
    {
      "owner": "ZichengXu",
      "repo": "lab-website",
      "date": "2024-12-17T22:07:52Z"
    },
    {
      "owner": "csjzhou",
      "repo": "hcai-lab.github.io",
      "date": "2024-12-14T03:07:35Z"
    },
    {
      "owner": "OliynykLab",
      "repo": "OliynykLab.github.io",
      "date": "2024-12-08T02:05:25Z"
    },
    {
      "owner": "hyICTlab",
      "repo": "hyICTlab.github.io",
      "date": "2024-11-28T06:32:39Z"
    },
    {
      "owner": "auburnseclab",
      "repo": "auburnseclab.github.io",
      "date": "2024-11-26T22:56:30Z"
    },
    {
      "owner": "fbaumdicker",
      "repo": "lab-website-template",
      "date": "2024-11-22T14:47:17Z"
    },
    {
      "owner": "SEA-ARMi",
      "repo": "SEA-ARMi.github.io",
      "date": "2024-11-22T08:38:50Z"
    },
    {
      "owner": "pheelab",
      "repo": "pheelab.github.io",
      "date": "2024-11-21T13:17:40Z"
    },
    {
      "owner": "256wangliu",
      "repo": "lab-website-template",
      "date": "2024-11-19T02:14:29Z"
    },
    {
      "owner": "KH-Fan",
      "repo": "FrankF_Lab",
      "date": "2024-11-06T15:47:10Z"
    },
    {
      "owner": "osimlab",
      "repo": "lab-website-template",
      "date": "2024-11-03T01:05:11Z"
    },
    {
      "owner": "PranavAchar01",
      "repo": "Anushma.",
      "date": "2024-10-19T04:29:13Z"
    },
    {
      "owner": "Haonan-Ling",
      "repo": "haonan-ling.github.io",
      "date": "2024-10-18T20:25:30Z"
    },
    {
      "owner": "proloyd",
      "repo": "lab-website",
      "date": "2024-10-18T14:57:24Z"
    },
    {
      "owner": "Ethanwithaheart",
      "repo": "lab-website-template",
      "date": "2024-10-14T14:51:19Z"
    },
    {
      "owner": "ranli-aphasia",
      "repo": "abrlab.github.io",
      "date": "2024-10-11T01:36:22Z"
    },
    {
      "owner": "Polster-lab",
      "repo": "polster-lab.github.io",
      "date": "2024-10-06T21:37:38Z"
    },
    {
      "owner": "aashmore",
      "repo": "aashmore.github.io",
      "date": "2024-10-05T21:23:26Z"
    },
    {
      "owner": "sydowpw",
      "repo": "sydowsymbiosis",
      "date": "2024-09-26T17:29:57Z"
    },
    {
      "owner": "ZMonfared",
      "repo": "MahshidBaharifar.github.io",
      "date": "2024-09-23T21:45:49Z"
    },
    {
      "owner": "perceptioncqu",
      "repo": "perception-group",
      "date": "2024-09-23T10:11:00Z"
    },
    {
      "owner": "EJC-Lab",
      "repo": "lab-website",
      "date": "2024-09-12T19:42:56Z"
    },
    {
      "owner": "weisgroup",
      "repo": "weisgroup.github.io",
      "date": "2024-09-12T03:44:16Z"
    },
    {
      "owner": "soumen-barman",
      "repo": "lab-website-template",
      "date": "2024-09-05T14:46:57Z"
    },
    {
      "owner": "yoongroup",
      "repo": "yoongroup.github.io",
      "date": "2024-08-26T12:39:59Z"
    },
    {
      "owner": "bhybhybhybhy",
      "repo": "yoongroup",
      "date": "2024-08-26T12:20:16Z"
    },
    {
      "owner": "StrangerLab",
      "repo": "lab-website-template",
      "date": "2024-08-22T11:19:54Z"
    },
    {
      "owner": "LeoTungAnh",
      "repo": "dual-lab-website-template",
      "date": "2024-08-14T02:42:35Z"
    },
    {
      "owner": "brorfred",
      "repo": "brorfred-labweb",
      "date": "2024-08-12T14:15:12Z"
    },
    {
      "owner": "BU-Neuromics",
      "repo": "neuromics-website",
      "date": "2024-08-09T16:47:27Z"
    },
    {
      "owner": "HammerSecurityLab",
      "repo": "hammersecuritylab.github.io",
      "date": "2024-08-07T03:40:08Z"
    },
    {
      "owner": "tasl-lab",
      "repo": "tasl-lab.github.io",
      "date": "2024-08-05T04:24:08Z"
    },
    {
      "owner": "depasquale-lab",
      "repo": "depasquale-lab.github.io",
      "date": "2024-08-03T00:54:43Z"
    },
    {
      "owner": "trongan93",
      "repo": "asv.github.io",
      "date": "2024-08-02T15:25:25Z"
    },
    {
      "owner": "afbat",
      "repo": "lab-website-template",
      "date": "2024-08-02T13:49:11Z"
    },
    {
      "owner": "kmjhyn",
      "repo": "lab-website-template",
      "date": "2024-07-29T14:19:31Z"
    },
    {
      "owner": "zzi4",
      "repo": "lab-website-template",
      "date": "2024-07-24T11:08:24Z"
    },
    {
      "owner": "FuturePISlack",
      "repo": "FuturePISlack.github.io",
      "date": "2024-07-23T19:45:24Z"
    },
    {
      "owner": "boseb",
      "repo": "Dr.-Banabithi-Bose",
      "date": "2024-07-23T05:04:03Z"
    },
    {
      "owner": "warren-lab",
      "repo": "warren-lab",
      "date": "2024-07-23T01:16:15Z"
    },
    {
      "owner": "yunyunwudal",
      "repo": "researchlab",
      "date": "2024-07-15T19:18:46Z"
    },
    {
      "owner": "Jinqiao-Li",
      "repo": "HC-AIL-Lab-Website",
      "date": "2024-07-15T07:10:04Z"
    },
    {
      "owner": "Yuchao-zhu",
      "repo": "Yuchao-zhu.github.io",
      "date": "2024-06-28T09:23:13Z"
    },
    {
      "owner": "ButlerPopSci",
      "repo": "butlerpopsci.github.io",
      "date": "2024-06-27T21:55:56Z"
    },
    {
      "owner": "rramosbaez",
      "repo": "rramosbaez-website",
      "date": "2024-06-20T20:41:28Z"
    },
    {
      "owner": "pkpare",
      "repo": "lab-website-template",
      "date": "2024-06-13T17:51:28Z"
    },
    {
      "owner": "waleedhasan1",
      "repo": "saban-lab",
      "date": "2024-06-07T00:31:45Z"
    },
    {
      "owner": "mlewis24",
      "repo": "pain-lab2-website",
      "date": "2024-05-23T19:21:26Z"
    },
    {
      "owner": "avvooturi",
      "repo": "kulik_website-template",
      "date": "2024-05-20T21:41:02Z"
    },
    {
      "owner": "TNBCLAB",
      "repo": "lab-website-template",
      "date": "2024-05-14T20:00:35Z"
    },
    {
      "owner": "xgdeng-SCU",
      "repo": "xgdeng-SCU",
      "date": "2024-05-13T06:25:56Z"
    },
    {
      "owner": "AbubakariAbdulwasid",
      "repo": "lab-website-template",
      "date": "2024-05-08T19:24:10Z"
    },
    {
      "owner": "PingchengDong",
      "repo": "vsdl_dpc.github.io",
      "date": "2024-05-08T07:44:35Z"
    },
    {
      "owner": "zhiyhu",
      "repo": "lab-website-template",
      "date": "2024-05-02T07:34:46Z"
    },
    {
      "owner": "nevaehRen",
      "repo": "mylab",
      "date": "2024-04-26T00:02:39Z"
    },
    {
      "owner": "qhmu",
      "repo": "qhmu.github.io",
      "date": "2024-04-18T12:46:58Z"
    },
    {
      "owner": "serenayj",
      "repo": "lab-website-template",
      "date": "2024-04-16T15:40:03Z"
    },
    {
      "owner": "liquidambar",
      "repo": "LanLiu-s-lab-website",
      "date": "2024-04-10T08:26:29Z"
    },
    {
      "owner": "ACLab-Bioinfo",
      "repo": "aclab_website_1.3.1",
      "date": "2024-04-10T07:24:56Z"
    },
    {
      "owner": "maximillanolotr",
      "repo": "lab-website-template",
      "date": "2024-04-04T17:01:14Z"
    },
    {
      "owner": "vtquang194",
      "repo": "lab-website-template",
      "date": "2024-03-31T14:18:35Z"
    },
    {
      "owner": "GraPharm-ML",
      "repo": "grapharm-ml.github.io",
      "date": "2024-03-22T18:35:27Z"
    },
    {
      "owner": "lasilab",
      "repo": "lab-website-template",
      "date": "2024-03-21T18:28:34Z"
    },
    {
      "owner": "eastlighting1",
      "repo": "test-lab.github.io",
      "date": "2024-03-15T14:12:47Z"
    },
    {
      "owner": "SidraEffendi",
      "repo": "mn_lab_website",
      "date": "2024-03-11T16:59:09Z"
    },
    {
      "owner": "shu4dev",
      "repo": "lab-website-template",
      "date": "2024-03-08T07:22:22Z"
    },
    {
      "owner": "Re-gen-web",
      "repo": "lab-website-template",
      "date": "2024-03-01T19:25:35Z"
    },
    {
      "owner": "wildbill12",
      "repo": "NobisLab-website",
      "date": "2024-02-29T19:37:15Z"
    },
    {
      "owner": "Maruuka",
      "repo": "lab-website-template",
      "date": "2024-02-27T01:00:02Z"
    },
    {
      "owner": "Patrick-Group",
      "repo": "Patrick-AI-Course-2024",
      "date": "2024-02-25T13:39:45Z"
    },
    {
      "owner": "ArtificialIoTLab",
      "repo": "aiotlab.github.io",
      "date": "2024-02-20T11:10:47Z"
    },
    {
      "owner": "deniseyael",
      "repo": "lab-website-template",
      "date": "2024-02-15T02:01:53Z"
    },
    {
      "owner": "changliu-99",
      "repo": "liu_lab",
      "date": "2024-02-02T18:45:01Z"
    },
    {
      "owner": "yam-turtle",
      "repo": "webpage",
      "date": "2024-02-01T06:33:50Z"
    },
    {
      "owner": "fffffeia",
      "repo": "222",
      "date": "2024-01-28T01:28:55Z"
    },
    {
      "owner": "THUSIGSDRMLAB",
      "repo": "lab-website-template",
      "date": "2024-01-26T08:19:44Z"
    },
    {
      "owner": "mcnoodle",
      "repo": "lab-website",
      "date": "2024-01-05T05:35:42Z"
    },
    {
      "owner": "shstat1729",
      "repo": "lab-website-template",
      "date": "2024-01-05T01:37:16Z"
    },
    {
      "owner": "Courtnie2894",
      "repo": "lab-website-template-STOLEN",
      "date": "2023-12-12T07:37:56Z"
    },
    {
      "owner": "SeqBioUCC",
      "repo": "lab-website",
      "date": "2023-12-10T19:43:32Z"
    },
    {
      "owner": "humphrey397",
      "repo": "SeqBioUCC",
      "date": "2023-12-10T19:10:27Z"
    },
    {
      "owner": "KojaAMA",
      "repo": "test2",
      "date": "2023-12-10T15:50:50Z"
    },
    {
      "owner": "OmDwivedi1237",
      "repo": "silverium-guidancium.github.io",
      "date": "2023-12-01T07:52:18Z"
    },
    {
      "owner": "chitranayak",
      "repo": "lab-website-template",
      "date": "2023-10-11T22:12:50Z"
    },
    {
      "owner": "YaleiYU",
      "repo": "lab-website-template",
      "date": "2023-10-02T16:18:55Z"
    },
    {
      "owner": "hellcodes",
      "repo": "lab-website-template",
      "date": "2023-09-22T19:21:06Z"
    },
    {
      "owner": "leylabdotorg",
      "repo": "lab-website",
      "date": "2023-09-14T02:56:39Z"
    },
    {
      "owner": "courtotlab",
      "repo": "courtotlab.github.io",
      "date": "2023-09-08T16:02:33Z"
    },
    {
      "owner": "lilin-bme",
      "repo": "lilin-bme.github.io",
      "date": "2023-09-04T03:09:51Z"
    },
    {
      "owner": "DMANSR",
      "repo": "lab-website-template",
      "date": "2023-09-02T06:44:49Z"
    },
    {
      "owner": "gr8lawrence",
      "repo": "gr8lawrence.github.io",
      "date": "2023-08-23T01:16:58Z"
    },
    {
      "owner": "NIOL-SUSTech",
      "repo": "NIOL-SUSTech.github.io",
      "date": "2023-08-14T08:09:09Z"
    },
    {
      "owner": "deadLabCary",
      "repo": "lab-website",
      "date": "2023-08-14T00:54:39Z"
    },
    {
      "owner": "Starlitnightly",
      "repo": "lab-website-template",
      "date": "2023-08-10T17:07:48Z"
    },
    {
      "owner": "NiSP-Q",
      "repo": "tNiSP-Q.github.io",
      "date": "2023-08-08T22:37:49Z"
    },
    {
      "owner": "praghav444",
      "repo": "xiangtaoxu.github.io",
      "date": "2023-08-06T04:41:40Z"
    },
    {
      "owner": "NoxLab-cam",
      "repo": "lab-website-template",
      "date": "2023-07-19T11:19:00Z"
    },
    {
      "owner": "yishakkibru",
      "repo": "lab-website-template",
      "date": "2023-07-19T06:22:43Z"
    },
    {
      "owner": "QinLiLab",
      "repo": "qinlilab.github.io",
      "date": "2023-07-13T20:04:52Z"
    },
    {
      "owner": "ZQadus",
      "repo": "lab-website-template",
      "date": "2023-06-29T21:38:48Z"
    },
    {
      "owner": "coder999",
      "repo": "diaslab",
      "date": "2023-06-21T01:11:34Z"
    },
    {
      "owner": "scd-github",
      "repo": "jsd-lab-website-template",
      "date": "2023-06-16T01:10:23Z"
    },
    {
      "owner": "papaemmelab",
      "repo": "papaemmelab",
      "date": "2023-06-09T22:05:27Z"
    },
    {
      "owner": "JianingWu911",
      "repo": "Homepage",
      "date": "2023-06-09T11:52:35Z"
    },
    {
      "owner": "AbdulkadirOzel",
      "repo": "baysanlab-website-template",
      "date": "2023-06-09T08:43:42Z"
    },
    {
      "owner": "snlab-hyu",
      "repo": "snlab-hyu.github.io",
      "date": "2023-06-05T10:13:20Z"
    },
    {
      "owner": "ozturkbaki",
      "repo": "lab-website-template",
      "date": "2023-05-19T15:17:42Z"
    },
    {
      "owner": "pena-rodrigo",
      "repo": "pena-rodrigo.github.io",
      "date": "2023-05-10T19:24:55Z"
    },
    {
      "owner": "gbsf7",
      "repo": "lab-jte",
      "date": "2023-05-05T01:03:52Z"
    },
    {
      "owner": "vonMentzer-Group",
      "repo": "lab-website-template",
      "date": "2023-04-29T07:27:47Z"
    },
    {
      "owner": "DepremKit",
      "repo": "depremkit.github.io",
      "date": "2023-04-25T17:03:01Z"
    },
    {
      "owner": "Minee-Liane-Choi",
      "repo": "lab-website-template",
      "date": "2023-04-25T01:40:57Z"
    },
    {
      "owner": "BinaryBlackhole",
      "repo": "lab-website",
      "date": "2023-04-17T04:58:55Z"
    },
    {
      "owner": "veyW",
      "repo": "PonomarovaLab",
      "date": "2023-04-15T21:12:10Z"
    },
    {
      "owner": "satpreetsingh",
      "repo": "lab-website-template",
      "date": "2023-04-13T14:25:31Z"
    },
    {
      "owner": "edkerk",
      "repo": "labpage",
      "date": "2023-04-12T09:13:35Z"
    },
    {
      "owner": "sjh960928",
      "repo": "sjh960928.github.io",
      "date": "2023-04-12T07:31:02Z"
    },
    {
      "owner": "nexgem25",
      "repo": "lab-website-template",
      "date": "2023-03-26T08:44:13Z"
    },
    {
      "owner": "Qi-X-Lab",
      "repo": "qix-lab",
      "date": "2023-03-23T09:53:21Z"
    },
    {
      "owner": "KwonVitalLab",
      "repo": "KwonVitalLab.github.io",
      "date": "2023-03-20T21:16:53Z"
    },
    {
      "owner": "MichaelZH24",
      "repo": "lab-website-template",
      "date": "2023-03-05T14:40:29Z"
    },
    {
      "owner": "masammons",
      "repo": "lab-website-template",
      "date": "2023-02-28T21:25:19Z"
    },
    {
      "owner": "anselmopaiva",
      "repo": "lab-website-template",
      "date": "2023-02-27T01:09:03Z"
    },
    {
      "owner": "drtomonroe",
      "repo": "lab-website-template",
      "date": "2023-02-22T17:49:51Z"
    },
    {
      "owner": "pivlab",
      "repo": "pivlab.org",
      "date": "2023-02-22T00:43:12Z"
    },
    {
      "owner": "jimjunker1",
      "repo": "lab-website-template",
      "date": "2023-02-17T18:54:46Z"
    },
    {
      "owner": "geowei1",
      "repo": "lab-website-template",
      "date": "2023-02-14T12:51:29Z"
    },
    {
      "owner": "avi-lab",
      "repo": "AviSahuAI",
      "date": "2023-02-02T14:15:57Z"
    },
    {
      "owner": "tongtybj",
      "repo": "lab-website",
      "date": "2023-02-01T15:32:44Z"
    },
    {
      "owner": "guanlinW",
      "repo": "WangLabWeb",
      "date": "2023-01-28T14:28:35Z"
    },
    {
      "owner": "cjgunase",
      "repo": "lab-website-template",
      "date": "2023-01-28T10:09:07Z"
    },
    {
      "owner": "Aequatio-Space",
      "repo": "Aequatio-Space.github.io",
      "date": "2023-01-23T12:52:49Z"
    },
    {
      "owner": "kaifuchenlab",
      "repo": "lab-website-template",
      "date": "2023-01-20T19:17:38Z"
    },
    {
      "owner": "ellisonlab",
      "repo": "ellison-lab-website",
      "date": "2023-01-18T15:15:13Z"
    },
    {
      "owner": "UcarLab",
      "repo": "ucarlab.github.io",
      "date": "2023-01-10T19:29:21Z"
    },
    {
      "owner": "GirayEryilmaz",
      "repo": "lab-website",
      "date": "2023-01-10T15:33:47Z"
    },
    {
      "owner": "majuiicb1981",
      "repo": "lab-website-template",
      "date": "2023-01-10T04:42:14Z"
    },
    {
      "owner": "ailab-mju",
      "repo": "test1",
      "date": "2023-01-07T07:21:51Z"
    },
    {
      "owner": "Mountchicken",
      "repo": "lab-website-template",
      "date": "2022-12-31T02:00:12Z"
    },
    {
      "owner": "buviar",
      "repo": "lab-website-template",
      "date": "2022-12-28T12:32:01Z"
    },
    {
      "owner": "cem-sevinc",
      "repo": "lab-website-template",
      "date": "2022-12-25T20:18:29Z"
    },
    {
      "owner": "ShouWenWang-Lab",
      "repo": "shouwenwang-lab.github.io",
      "date": "2022-12-11T03:34:43Z"
    },
    {
      "owner": "VarshaSinghIIT",
      "repo": "WebPage",
      "date": "2022-12-10T08:21:37Z"
    },
    {
      "owner": "filipebraida",
      "repo": "atislabs_wiped2",
      "date": "2022-12-06T14:24:57Z"
    },
    {
      "owner": "alexmsalmeida",
      "repo": "lab-website-template",
      "date": "2022-12-01T13:04:11Z"
    },
    {
      "owner": "Shawn-hub-hit",
      "repo": "lab-website-template",
      "date": "2022-11-27T07:51:37Z"
    },
    {
      "owner": "jieguann",
      "repo": "lab-website-template",
      "date": "2022-11-23T18:40:19Z"
    },
    {
      "owner": "salt-centai",
      "repo": "salt-centai.github.io",
      "date": "2022-11-20T13:41:07Z"
    },
    {
      "owner": "Tommyxjs",
      "repo": "lab-website-template",
      "date": "2022-11-20T13:34:38Z"
    },
    {
      "owner": "falquaddoomi",
      "repo": "lab-website-template",
      "date": "2022-11-16T16:46:00Z"
    },
    {
      "owner": "ch728",
      "repo": "lab-website-template",
      "date": "2022-11-10T02:04:13Z"
    },
    {
      "owner": "bu-mseen",
      "repo": "Denis-Lab.github.io",
      "date": "2022-11-09T18:45:16Z"
    },
    {
      "owner": "jbrendecke",
      "repo": "UArizona-Libera",
      "date": "2022-11-08T21:15:22Z"
    },
    {
      "owner": "Aleksobrad",
      "repo": "aleksobrad.github.io",
      "date": "2022-10-30T02:44:16Z"
    },
    {
      "owner": "LM-Ince",
      "repo": "lab-website-ince",
      "date": "2022-10-22T16:28:53Z"
    },
    {
      "owner": "YangLab2022",
      "repo": "lab-website-template",
      "date": "2022-10-21T03:20:49Z"
    },
    {
      "owner": "learlab",
      "repo": "learlab.github.io",
      "date": "2022-10-20T23:16:16Z"
    },
    {
      "owner": "jcole150",
      "repo": "jcole-lab-website",
      "date": "2022-10-14T18:40:21Z"
    },
    {
      "owner": "abel-sysu",
      "repo": "lab-website-template",
      "date": "2022-10-09T12:38:19Z"
    },
    {
      "owner": "drosinis",
      "repo": "lab-website-template",
      "date": "2022-10-08T16:58:00Z"
    },
    {
      "owner": "sawinlab",
      "repo": "sawinlab.github.io",
      "date": "2022-10-08T09:18:37Z"
    },
    {
      "owner": "goallabuci",
      "repo": "lab-website-template",
      "date": "2022-10-04T21:58:38Z"
    },
    {
      "owner": "steliostavroulakis",
      "repo": "lab-website-template",
      "date": "2022-10-04T00:07:52Z"
    },
    {
      "owner": "MusculusMus",
      "repo": "lab-website-template",
      "date": "2022-10-03T19:26:53Z"
    },
    {
      "owner": "yluo86",
      "repo": "luo-lab-website",
      "date": "2022-09-27T21:16:28Z"
    },
    {
      "owner": "mahdipedro",
      "repo": "lab-website-template",
      "date": "2022-09-26T00:26:35Z"
    },
    {
      "owner": "keuperj",
      "repo": "keuper-labs",
      "date": "2022-09-25T09:54:46Z"
    },
    {
      "owner": "sidney1994",
      "repo": "lab-website-template",
      "date": "2022-09-20T08:31:53Z"
    },
    {
      "owner": "CirculatoryHealth",
      "repo": "kai6662.github.io",
      "date": "2022-09-15T21:34:44Z"
    },
    {
      "owner": "tchen-tt",
      "repo": "lab-website-template",
      "date": "2022-09-09T16:04:48Z"
    },
    {
      "owner": "zhongyuan1996",
      "repo": "PSU-DataScience",
      "date": "2022-09-02T18:37:08Z"
    },
    {
      "owner": "xueliktz",
      "repo": "lab-website-template",
      "date": "2022-09-02T01:53:19Z"
    },
    {
      "owner": "anphu7492",
      "repo": "ideaslab.github.io",
      "date": "2022-08-31T21:50:01Z"
    },
    {
      "owner": "sean8purdue",
      "repo": "lab-website-template1",
      "date": "2022-08-29T01:11:46Z"
    },
    {
      "owner": "weinberz",
      "repo": "witchlab",
      "date": "2022-08-21T16:34:07Z"
    },
    {
      "owner": "mistriotis-lab",
      "repo": "lab-website-template",
      "date": "2022-08-18T18:34:35Z"
    },
    {
      "owner": "luhugerth",
      "repo": "hugabug",
      "date": "2022-08-10T08:57:38Z"
    },
    {
      "owner": "NeuroCognitiveImagingLab",
      "repo": "NCIL-Working-Website",
      "date": "2022-07-28T14:51:05Z"
    },
    {
      "owner": "fontenaslab",
      "repo": "lab-website-template",
      "date": "2022-07-20T00:24:08Z"
    },
    {
      "owner": "LaBiOmicS",
      "repo": "labiomics.github.io",
      "date": "2022-07-09T22:10:06Z"
    },
    {
      "owner": "HuangZY2",
      "repo": "HuangZY2.github.io",
      "date": "2022-06-29T02:07:13Z"
    },
    {
      "owner": "dama-lab",
      "repo": "dmac-lab.github.io",
      "date": "2022-06-15T21:59:53Z"
    },
    {
      "owner": "lukjh",
      "repo": "lab-website-template",
      "date": "2022-06-04T04:41:22Z"
    },
    {
      "owner": "sdiciotti",
      "repo": "lab-website-template",
      "date": "2022-06-01T14:51:15Z"
    },
    {
      "owner": "EmmaKelley",
      "repo": "lab-website-template",
      "date": "2022-05-31T21:06:19Z"
    },
    {
      "owner": "AiluroMind",
      "repo": "lab-website-template",
      "date": "2022-05-20T11:31:23Z"
    },
    {
      "owner": "37HAN",
      "repo": "websea.github.io",
      "date": "2022-05-13T06:57:12Z"
    },
    {
      "owner": "diazgarcia",
      "repo": "diazgarcia.github.io",
      "date": "2022-05-12T20:08:43Z"
    },
    {
      "owner": "erikvandenakker",
      "repo": "lab-website-template",
      "date": "2022-04-30T21:56:04Z"
    },
    {
      "owner": "HershbergerLab",
      "repo": "hershlab-website",
      "date": "2022-04-29T17:09:17Z"
    },
    {
      "owner": "JingqiuLiao",
      "repo": "lab-website-template",
      "date": "2022-04-25T15:22:03Z"
    },
    {
      "owner": "Evo-MInt",
      "repo": "lab-website-template",
      "date": "2022-04-24T12:51:54Z"
    },
    {
      "owner": "mohit-iitb",
      "repo": "mohit-iitb.github",
      "date": "2022-04-20T19:30:48Z"
    },
    {
      "owner": "tommyngx",
      "repo": "lab-website-template",
      "date": "2022-04-17T02:36:14Z"
    },
    {
      "owner": "skyofyao",
      "repo": "lab-website-template",
      "date": "2022-04-14T07:52:15Z"
    },
    {
      "owner": "doxeylab",
      "repo": "lab-website-template",
      "date": "2022-04-10T16:58:02Z"
    },
    {
      "owner": "minglibio",
      "repo": "lab-website-template",
      "date": "2022-04-04T21:46:53Z"
    },
    {
      "owner": "Ellison0920",
      "repo": "lab-website-template",
      "date": "2022-04-04T18:02:33Z"
    },
    {
      "owner": "VenkteshV",
      "repo": "lab-website-template",
      "date": "2022-03-19T19:50:31Z"
    },
    {
      "owner": "AurapatN",
      "repo": "CRIwebtest",
      "date": "2022-03-11T11:02:28Z"
    },
    {
      "owner": "joanPlepi",
      "repo": "lab-website-template",
      "date": "2022-03-08T09:56:43Z"
    },
    {
      "owner": "mscherzer",
      "repo": "lab-website-template",
      "date": "2022-02-17T18:41:07Z"
    },
    {
      "owner": "fuqw00",
      "repo": "lab-website-template",
      "date": "2022-02-16T22:54:20Z"
    },
    {
      "owner": "ml-morphogen",
      "repo": "lab-website-template",
      "date": "2022-02-14T01:43:54Z"
    },
    {
      "owner": "biostat0903",
      "repo": "biostat0903.github.io",
      "date": "2022-02-07T08:23:34Z"
    },
    {
      "owner": "hamilton101",
      "repo": "hamilton101.github.io",
      "date": "2022-02-05T22:26:22Z"
    },
    {
      "owner": "Evavives",
      "repo": "lab-website-template",
      "date": "2022-02-05T20:26:32Z"
    },
    {
      "owner": "mingfaifong",
      "repo": "lab-website-template",
      "date": "2022-02-04T21:53:42Z"
    },
    {
      "owner": "CU-DBMI",
      "repo": "set-website",
      "date": "2022-01-13T03:40:55Z"
    },
    {
      "owner": "linwang98",
      "repo": "lab-website-template",
      "date": "2021-12-15T20:30:40Z"
    },
    {
      "owner": "burkesquires",
      "repo": "lab-website-template",
      "date": "2021-12-06T13:13:40Z"
    },
    {
      "owner": "MMB-UMCU",
      "repo": "mmb-bioit",
      "date": "2021-11-25T13:42:15Z"
    },
    {
      "owner": "sarahrmoeller",
      "repo": "meldlab",
      "date": "2021-11-12T20:08:15Z"
    },
    {
      "owner": "J1Souza",
      "repo": "lab-website-template",
      "date": "2021-11-10T02:02:15Z"
    },
    {
      "owner": "weiserevanslab",
      "repo": "weiserevanslab",
      "date": "2021-11-09T22:41:36Z"
    },
    {
      "owner": "UNCBiomedicalComp",
      "repo": "UNCBiomedicalComp.github.io",
      "date": "2021-10-05T01:22:28Z"
    },
    {
      "owner": "dmwalker-dmw",
      "repo": "lab-website-template",
      "date": "2021-09-07T23:04:54Z"
    },
    {
      "owner": "1KFG",
      "repo": "1kfg.github.io",
      "date": "2021-08-23T03:10:09Z"
    },
    {
      "owner": "zygolife",
      "repo": "zygolife.github.io",
      "date": "2021-08-23T03:08:58Z"
    },
    {
      "owner": "stajichlab",
      "repo": "stajichlab.github.io",
      "date": "2021-08-17T07:31:58Z"
    },
    {
      "owner": "WayScience",
      "repo": "lab-website-template",
      "date": "2021-08-11T18:22:08Z"
    },
    {
      "owner": "krishnatejakk",
      "repo": "MLO-LAB",
      "date": "2021-07-30T18:01:52Z"
    },
    {
      "owner": "BioMeCIS",
      "repo": "biomecis.github.io",
      "date": "2021-07-22T22:09:35Z"
    },
    {
      "owner": "DucHung1901",
      "repo": "lab-website-template",
      "date": "2021-07-20T14:57:30Z"
    },
    {
      "owner": "selabhust",
      "repo": "lab-website-template",
      "date": "2021-07-20T14:38:32Z"
    },
    {
      "owner": "donghaiwu",
      "repo": "xiangtaoxu.github.io",
      "date": "2021-07-15T18:41:23Z"
    },
    {
      "owner": "MeiDu01",
      "repo": "lab-website-template",
      "date": "2021-07-14T08:03:28Z"
    },
    {
      "owner": "smartenergylabsee",
      "repo": "lab-website-template",
      "date": "2021-07-13T15:02:32Z"
    },
    {
      "owner": "monkiravn",
      "repo": "lab-website-template",
      "date": "2021-07-13T14:23:17Z"
    },
    {
      "owner": "johannesnicolaus",
      "repo": "lab-website-template",
      "date": "2021-07-07T00:00:22Z"
    },
    {
      "owner": "Hossein-Fallahi",
      "repo": "lab-website-template",
      "date": "2021-06-29T11:22:52Z"
    },
    {
      "owner": "moraesfernanda",
      "repo": "lab-website-template",
      "date": "2021-06-29T02:03:51Z"
    },
    {
      "owner": "LabHutchison",
      "repo": "lab-website-template",
      "date": "2021-06-29T02:00:01Z"
    },
    {
      "owner": "jxchen01",
      "repo": "lab-website-template",
      "date": "2021-06-12T03:22:06Z"
    },
    {
      "owner": "fong-lab",
      "repo": "fong-lab-old-website",
      "date": "2021-05-27T14:57:24Z"
    },
    {
      "owner": "eastonwhite",
      "repo": "lab-website-template",
      "date": "2021-04-18T19:14:02Z"
    },
    {
      "owner": "QuantMarineEcoLab",
      "repo": "quantmarineecolab.github.io",
      "date": "2021-04-06T11:50:50Z"
    },
    {
      "owner": "edyoshikun",
      "repo": "lab-website-template",
      "date": "2021-04-06T04:19:17Z"
    },
    {
      "owner": "rando2",
      "repo": "lab-website-template",
      "date": "2021-03-25T15:15:50Z"
    },
    {
      "owner": "standardgalactic",
      "repo": "lab-website-template",
      "date": "2021-02-10T17:50:25Z"
    },
    {
      "owner": "Chebuu",
      "repo": "lab-website-template",
      "date": "2021-01-30T12:06:27Z"
    },
    {
      "owner": "philno",
      "repo": "lab-website-template",
      "date": "2021-01-15T09:54:21Z"
    },
    {
      "owner": "rnabioco",
      "repo": "lab-website-template",
      "date": "2020-12-12T17:38:37Z"
    },
    {
      "owner": "caisa-lab",
      "repo": "caisa-lab.github.io",
      "date": "2020-12-06T13:48:10Z"
    },
    {
      "owner": "juexinwang",
      "repo": "lab-website-template",
      "date": "2020-11-24T13:39:39Z"
    },
    {
      "owner": "vcheplygina",
      "repo": "lab-website-template",
      "date": "2020-11-21T08:53:45Z"
    },
    {
      "owner": "npomb001",
      "repo": "lab-website-template",
      "date": "2020-11-06T23:16:41Z"
    }
  ],
  "overTime": [
    {
      "date": "2020-11-01T04:00:00.000Z",
      "count": 0
    },
    {
      "date": "2020-12-01T05:00:00.000Z",
      "count": 3
    },
    {
      "date": "2021-01-01T05:00:00.000Z",
      "count": 5
    },
    {
      "date": "2021-02-01T05:00:00.000Z",
      "count": 7
    },
    {
      "date": "2021-03-01T05:00:00.000Z",
      "count": 8
    },
    {
      "date": "2021-04-01T04:00:00.000Z",
      "count": 9
    },
    {
      "date": "2021-05-01T04:00:00.000Z",
      "count": 12
    },
    {
      "date": "2021-06-01T04:00:00.000Z",
      "count": 13
    },
    {
      "date": "2021-07-01T04:00:00.000Z",
      "count": 17
    },
    {
      "date": "2021-08-01T04:00:00.000Z",
      "count": 26
    },
    {
      "date": "2021-09-01T04:00:00.000Z",
      "count": 30
    },
    {
      "date": "2021-10-01T04:00:00.000Z",
      "count": 31
    },
    {
      "date": "2021-11-01T04:00:00.000Z",
      "count": 32
    },
    {
      "date": "2021-12-01T05:00:00.000Z",
      "count": 36
    },
    {
      "date": "2022-01-01T05:00:00.000Z",
      "count": 38
    },
    {
      "date": "2022-02-01T05:00:00.000Z",
      "count": 39
    },
    {
      "date": "2022-03-01T05:00:00.000Z",
      "count": 46
    },
    {
      "date": "2022-04-01T04:00:00.000Z",
      "count": 49
    },
    {
      "date": "2022-05-01T04:00:00.000Z",
      "count": 59
    },
    {
      "date": "2022-06-01T04:00:00.000Z",
      "count": 63
    },
    {
      "date": "2022-07-01T04:00:00.000Z",
      "count": 67
    },
    {
      "date": "2022-08-01T04:00:00.000Z",
      "count": 70
    },
    {
      "date": "2022-09-01T04:00:00.000Z",
      "count": 75
    },
    {
      "date": "2022-10-01T04:00:00.000Z",
      "count": 83
    },
    {
      "date": "2022-11-01T04:00:00.000Z",
      "count": 94
    },
    {
      "date": "2022-12-01T05:00:00.000Z",
      "count": 102
    },
    {
      "date": "2023-01-01T05:00:00.000Z",
      "count": 109
    },
    {
      "date": "2023-02-01T05:00:00.000Z",
      "count": 118
    },
    {
      "date": "2023-03-01T05:00:00.000Z",
      "count": 126
    },
    {
      "date": "2023-04-01T04:00:00.000Z",
      "count": 130
    },
    {
      "date": "2023-05-01T04:00:00.000Z",
      "count": 138
    },
    {
      "date": "2023-06-01T04:00:00.000Z",
      "count": 141
    },
    {
      "date": "2023-07-01T04:00:00.000Z",
      "count": 148
    },
    {
      "date": "2023-08-01T04:00:00.000Z",
      "count": 151
    },
    {
      "date": "2023-09-01T04:00:00.000Z",
      "count": 157
    },
    {
      "date": "2023-10-01T04:00:00.000Z",
      "count": 162
    },
    {
      "date": "2023-11-01T04:00:00.000Z",
      "count": 164
    },
    {
      "date": "2023-12-01T05:00:00.000Z",
      "count": 164
    },
    {
      "date": "2024-01-01T05:00:00.000Z",
      "count": 169
    },
    {
      "date": "2024-02-01T05:00:00.000Z",
      "count": 173
    },
    {
      "date": "2024-03-01T05:00:00.000Z",
      "count": 180
    },
    {
      "date": "2024-04-01T04:00:00.000Z",
      "count": 187
    },
    {
      "date": "2024-05-01T04:00:00.000Z",
      "count": 193
    },
    {
      "date": "2024-06-01T04:00:00.000Z",
      "count": 200
    },
    {
      "date": "2024-07-01T04:00:00.000Z",
      "count": 205
    },
    {
      "date": "2024-08-01T04:00:00.000Z",
      "count": 212
    },
    {
      "date": "2024-09-01T04:00:00.000Z",
      "count": 223
    },
    {
      "date": "2024-10-01T04:00:00.000Z",
      "count": 229
    },
    {
      "date": "2024-11-01T04:00:00.000Z",
      "count": 236
    },
    {
      "date": "2024-12-01T05:00:00.000Z",
      "count": 244
    },
    {
      "date": "2025-01-01T05:00:00.000Z",
      "count": 248
    },
    {
      "date": "2025-02-01T05:00:00.000Z",
      "count": 255
    },
    {
      "date": "2025-03-01T05:00:00.000Z",
      "count": 265
    },
    {
      "date": "2025-04-01T04:00:00.000Z",
      "count": 275
    },
    {
      "date": "2025-05-01T04:00:00.000Z",
      "count": 283
    },
    {
      "date": "2025-06-01T04:00:00.000Z",
      "count": 293
    },
    {
      "date": "2025-07-01T04:00:00.000Z",
      "count": 303
    },
    {
      "date": "2025-08-01T04:00:00.000Z",
      "count": 316
    }
  ]
}