[
  {
    "date": "2020-11-01T04:00:00.000Z",
    "count": 0
  },
  {
    "date": "2020-12-01T05:00:00.000Z",
    "count": 3
  },
  {
    "date": "2021-01-01T05:00:00.000Z",
    "count": 5
  },
  {
    "date": "2021-02-01T05:00:00.000Z",
    "count": 7
  },
  {
    "date": "2021-03-01T05:00:00.000Z",
    "count": 8
  },
  {
    "date": "2021-04-01T04:00:00.000Z",
    "count": 9
  },
  {
    "date": "2021-05-01T04:00:00.000Z",
    "count": 12
  },
  {
    "date": "2021-06-01T04:00:00.000Z",
    "count": 13
  },
  {
    "date": "2021-07-01T04:00:00.000Z",
    "count": 17
  },
  {
    "date": "2021-08-01T04:00:00.000Z",
    "count": 26
  },
  {
    "date": "2021-09-01T04:00:00.000Z",
    "count": 30
  },
  {
    "date": "2021-10-01T04:00:00.000Z",
    "count": 31
  },
  {
    "date": "2021-11-01T04:00:00.000Z",
    "count": 32
  },
  {
    "date": "2021-12-01T05:00:00.000Z",
    "count": 36
  },
  {
    "date": "2022-01-01T05:00:00.000Z",
    "count": 38
  },
  {
    "date": "2022-02-01T05:00:00.000Z",
    "count": 39
  },
  {
    "date": "2022-03-01T05:00:00.000Z",
    "count": 46
  },
  {
    "date": "2022-04-01T04:00:00.000Z",
    "count": 49
  },
  {
    "date": "2022-05-01T04:00:00.000Z",
    "count": 59
  },
  {
    "date": "2022-06-01T04:00:00.000Z",
    "count": 63
  },
  {
    "date": "2022-07-01T04:00:00.000Z",
    "count": 67
  },
  {
    "date": "2022-08-01T04:00:00.000Z",
    "count": 70
  },
  {
    "date": "2022-09-01T04:00:00.000Z",
    "count": 75
  },
  {
    "date": "2022-10-01T04:00:00.000Z",
    "count": 83
  },
  {
    "date": "2022-11-01T04:00:00.000Z",
    "count": 94
  },
  {
    "date": "2022-12-01T05:00:00.000Z",
    "count": 102
  },
  {
    "date": "2023-01-01T05:00:00.000Z",
    "count": 109
  },
  {
    "date": "2023-02-01T05:00:00.000Z",
    "count": 118
  },
  {
    "date": "2023-03-01T05:00:00.000Z",
    "count": 126
  },
  {
    "date": "2023-04-01T04:00:00.000Z",
    "count": 130
  },
  {
    "date": "2023-05-01T04:00:00.000Z",
    "count": 138
  },
  {
    "date": "2023-06-01T04:00:00.000Z",
    "count": 141
  },
  {
    "date": "2023-07-01T04:00:00.000Z",
    "count": 148
  },
  {
    "date": "2023-08-01T04:00:00.000Z",
    "count": 151
  },
  {
    "date": "2023-09-01T04:00:00.000Z",
    "count": 157
  },
  {
    "date": "2023-10-01T04:00:00.000Z",
    "count": 162
  },
  {
    "date": "2023-11-01T04:00:00.000Z",
    "count": 164
  },
  {
    "date": "2023-12-01T05:00:00.000Z",
    "count": 164
  },
  {
    "date": "2024-01-01T05:00:00.000Z",
    "count": 169
  },
  {
    "date": "2024-02-01T05:00:00.000Z",
    "count": 173
  },
  {
    "date": "2024-03-01T05:00:00.000Z",
    "count": 180
  },
  {
    "date": "2024-04-01T04:00:00.000Z",
    "count": 187
  },
  {
    "date": "2024-05-01T04:00:00.000Z",
    "count": 193
  },
  {
    "date": "2024-06-01T04:00:00.000Z",
    "count": 200
  },
  {
    "date": "2024-07-01T04:00:00.000Z",
    "count": 205
  },
  {
    "date": "2024-08-01T04:00:00.000Z",
    "count": 212
  },
  {
    "date": "2024-09-01T04:00:00.000Z",
    "count": 223
  },
  {
    "date": "2024-10-01T04:00:00.000Z",
    "count": 229
  },
  {
    "date": "2024-11-01T04:00:00.000Z",
    "count": 236
  },
  {
    "date": "2024-12-01T05:00:00.000Z",
    "count": 244
  },
  {
    "date": "2025-01-01T05:00:00.000Z",
    "count": 248
  },
  {
    "date": "2025-02-01T05:00:00.000Z",
    "count": 255
  },
  {
    "date": "2025-03-01T05:00:00.000Z",
    "count": 265
  },
  {
    "date": "2025-04-01T04:00:00.000Z",
    "count": 275
  },
  {
    "date": "2025-05-01T04:00:00.000Z",
    "count": 283
  },
  {
    "date": "2025-06-01T04:00:00.000Z",
    "count": 293
  },
  {
    "date": "2025-07-01T04:00:00.000Z",
    "count": 303
  }
]