[
  {
    "owner": "greenelab",
    "repo": "greenelab.com",
    "date": "2022-02-01T21:28:51.000Z"
  },
  {
    "owner": "greenelab",
    "repo": "lab-website-template",
    "date": "2021-08-14T20:46:21.000Z"
  },
  {
    "owner": "WayScience",
    "repo": "waysciencelab.com",
    "date": "2021-08-11T18:25:43.000Z"
  },
  {
    "owner": "tis-lab",
    "repo": "tislab.org",
    "date": "2022-02-01T18:30:24.000Z"
  },
  {
    "owner": "ACManoa",
    "repo": "acmanoa.github.io",
    "date": "2024-03-23T11:25:30.000Z"
  },
  {
    "owner": "SuLab",
    "repo": "sulab.org",
    "date": "2021-08-14T20:46:21.000Z"
  },
  {
    "owner": "MMV-Lab",
    "repo": "mmv-lab.github.io-backup",
    "date": "2021-05-27T17:06:47.000Z"
  },
  {
    "owner": "airvitap",
    "repo": "airvitap.github.io",
    "date": "2024-10-04T09:45:40.000Z"
  },
  {
    "owner": "solecnugit",
    "repo": "solecnugit.github.io",
    "date": "2024-04-03T06:39:24.000Z"
  },
  {
    "owner": "RIM-Laboratory",
    "repo": "RIM-Laboratory.github.io",
    "date": "2023-09-10T05:57:55.000Z"
  },
  {
    "owner": "ucf-draco-lab",
    "repo": "draco-website",
    "date": "2024-07-23T21:35:46.000Z"
  },
  {
    "owner": "ireneg",
    "repo": "hge-lab",
    "date": "2021-08-14T20:46:21.000Z"
  },
  {
    "owner": "pivlab",
    "repo": "pivlab-website",
    "date": "2021-08-14T20:46:21.000Z"
  },
  {
    "owner": "vbilsmith",
    "repo": "vbilsmith.github.io",
    "date": "2023-08-07T16:54:20.000Z"
  },
  {
    "owner": "RUC-NLPIR",
    "repo": "RUC-NLPIR.github.io",
    "date": "2024-03-12T02:58:17.000Z"
  },
  {
    "owner": "tiansheng-zhu",
    "repo": "tian_xing",
    "date": "2024-07-16T14:06:10.000Z"
  },
  {
    "owner": "korthauer-lab",
    "repo": "korthauer-lab.github.io",
    "date": "2021-08-14T20:46:21.000Z"
  },
  {
    "owner": "dashnowlab",
    "repo": "lab-website",
    "date": "2021-08-14T20:46:21.000Z"
  },
  {
    "owner": "WOOSEUNGHOON",
    "repo": "ssp",
    "date": "2023-08-16T05:45:00.000Z"
  },
  {
    "owner": "sensationinmotion",
    "repo": "sensationinmotion.github.io",
    "date": "2022-05-25T15:47:31.000Z"
  },
  {
    "owner": "BisanzLab",
    "repo": "bisanzlab.github.io",
    "date": "2023-10-04T13:36:38.000Z"
  },
  {
    "owner": "dalmolingroup",
    "repo": "dalmolingroup.github.io",
    "date": "2023-12-13T01:00:31.000Z"
  },
  {
    "owner": "RifeLab",
    "repo": "RifeLab.org",
    "date": "2021-08-14T20:46:21.000Z"
  },
  {
    "owner": "Lindsay-Lab",
    "repo": "lindsay-lab.github.io",
    "date": "2022-10-03T15:26:17.000Z"
  },
  {
    "owner": "rcarcamo-dot",
    "repo": "website",
    "date": "2022-10-26T09:45:00.000Z"
  },
  {
    "owner": "AIS-SNU",
    "repo": "AIS-lab-website",
    "date": "2024-02-25T12:41:29.000Z"
  },
  {
    "owner": "MMV-Lab",
    "repo": "mmv-lab.github.io",
    "date": "2021-08-14T20:46:21.000Z"
  },
  {
    "owner": "HUSTLYRM",
    "repo": "langya_website",
    "date": "2024-10-18T23:58:51.000Z"
  },
  {
    "owner": "infovisions",
    "repo": "infovisions.github.io",
    "date": "2024-12-19T21:47:14.000Z"
  },
  {
    "owner": "metaBIOlab",
    "repo": "metabio",
    "date": "2021-06-28T21:23:13.000Z"
  },
  {
    "owner": "Computational-Morphogenomics-Group",
    "repo": "cmg-old-website",
    "date": "2021-08-14T20:46:21.000Z"
  },
  {
    "owner": "guangyaoz",
    "repo": "vova-lab.github.io",
    "date": "2024-12-17T22:01:05.000Z"
  },
  {
    "owner": "nimo-group",
    "repo": "nimo-website",
    "date": "2025-06-21T13:51:52.000Z"
  },
  {
    "owner": "drieslab",
    "repo": "drieslab2",
    "date": "2022-05-24T18:47:19.000Z"
  },
  {
    "owner": "EvoCatalysis",
    "repo": "evocatalysis.github.io",
    "date": "2023-06-13T02:56:43.000Z"
  },
  {
    "owner": "bfscheve",
    "repo": "CDNlab",
    "date": "2024-07-29T19:40:51.000Z"
  },
  {
    "owner": "EpiForeSITE",
    "repo": "ForeSITE_Website",
    "date": "2024-05-03T17:29:14.000Z"
  },
  {
    "owner": "hustvl",
    "repo": "hustvl.github.io",
    "date": "2024-02-14T08:31:26.000Z"
  },
  {
    "owner": "dimi-lab",
    "repo": "dimi-lab.github.io",
    "date": "2023-10-27T17:11:37.000Z"
  },
  {
    "owner": "gastrovirus-uv",
    "repo": "gastro_website",
    "date": "2022-10-25T10:37:07.000Z"
  },
  {
    "owner": "innovative-robotics",
    "repo": "innovative-robotics.github.io",
    "date": "2022-09-13T18:55:13.000Z"
  },
  {
    "owner": "mistriotis-lab",
    "repo": "mistriotis-lab.github.io",
    "date": "2021-07-11T17:25:57.000Z"
  },
  {
    "owner": "2533245542",
    "repo": "mooney_lab.github.io",
    "date": "2022-05-30T17:45:07.000Z"
  },
  {
    "owner": "velten-group",
    "repo": "velten-group.github.io",
    "date": "2021-08-14T20:46:21.000Z"
  },
  {
    "owner": "THUNAME",
    "repo": "lab-website",
    "date": "2025-01-13T12:56:13.000Z"
  },
  {
    "owner": "hulmanlab",
    "repo": "webpage",
    "date": "2023-04-04T10:52:06.000Z"
  },
  {
    "owner": "khan-lab",
    "repo": "khan-lab.github.io",
    "date": "2025-03-07T08:43:00.000Z"
  },
  {
    "owner": "csl-lab-upenn",
    "repo": "csl-lab-upenn.github.io",
    "date": "2023-03-09T22:35:25.000Z"
  },
  {
    "owner": "tup-robomaster",
    "repo": "tup-lab-website",
    "date": "2025-06-08T06:50:28.000Z"
  },
  {
    "owner": "gatech-sysml",
    "repo": "gatech-sysml.github.io",
    "date": "2024-03-10T04:08:06.000Z"
  },
  {
    "owner": "christianbrodbeck",
    "repo": "lab-website",
    "date": "2024-10-17T15:25:18.000Z"
  },
  {
    "owner": "nycu-acm",
    "repo": "ACM_NYCU_website",
    "date": "2024-12-03T07:07:40.000Z"
  },
  {
    "owner": "PolyU-TASLAB",
    "repo": "polyu-taslab.github.io",
    "date": "2024-12-06T04:22:44.000Z"
  },
  {
    "owner": "Ericsson",
    "repo": "cognitive-labs",
    "date": "2023-12-17T19:30:38.000Z"
  },
  {
    "owner": "PHB-Methods",
    "repo": "phb-methoden-website",
    "date": "2024-07-04T13:04:57.000Z"
  },
  {
    "owner": "Schulze-lab",
    "repo": "Schulze-lab-website",
    "date": "2022-09-05T19:00:59.000Z"
  },
  {
    "owner": "juergen-pfeffermann",
    "repo": "website",
    "date": "2022-10-06T17:41:53.000Z"
  },
  {
    "owner": "fengyueguo",
    "repo": "Med_AIR_LABWEB",
    "date": "2025-05-07T05:35:56.000Z"
  },
  {
    "owner": "academix0",
    "repo": "academix0.github.io",
    "date": "2025-04-03T23:12:24.000Z"
  },
  {
    "owner": "AKS-DHLAB",
    "repo": "AKS_DHLab_Website",
    "date": "2025-02-18T05:04:36.000Z"
  },
  {
    "owner": "cisnerosatcharlotte",
    "repo": "cisnerosatcharlotte.github.io",
    "date": "2021-08-14T20:46:21.000Z"
  },
  {
    "owner": "time-lab-ml",
    "repo": "time-lab-ml.github.io",
    "date": "2025-02-05T02:33:27.000Z"
  },
  {
    "owner": "BMGLab",
    "repo": "bmglab.github.io",
    "date": "2023-01-24T09:18:02.000Z"
  },
  {
    "owner": "englertlab",
    "repo": "EnglertLab_2.0",
    "date": "2023-11-24T17:09:30.000Z"
  },
  {
    "owner": "QUANTA-Research-Group",
    "repo": "quanta-research-group.github.io",
    "date": "2025-04-04T20:19:11.000Z"
  },
  {
    "owner": "YTianZHU",
    "repo": "LeapLabTHU",
    "date": "2024-04-24T16:39:49.000Z"
  },
  {
    "owner": "Bednar-lab",
    "repo": "bednarlab",
    "date": "2022-11-01T03:26:26.000Z"
  },
  {
    "owner": "DDPSE",
    "repo": "DDPSE.github.io",
    "date": "2023-10-09T02:33:26.000Z"
  },
  {
    "owner": "johannessonlab",
    "repo": "johannessonlab.github.io",
    "date": "2023-02-27T10:01:38.000Z"
  },
  {
    "owner": "epifluidlab",
    "repo": "epifluidlab.github.io",
    "date": "2022-08-12T18:37:34.000Z"
  },
  {
    "owner": "inspirelab-site",
    "repo": "inspirelab.site",
    "date": "2024-07-31T00:06:46.000Z"
  },
  {
    "owner": "inspirelab-site",
    "repo": "inspirelab.umd.edu",
    "date": "2024-07-31T00:06:46.000Z"
  },
  {
    "owner": "filrg",
    "repo": "filrg.github.io",
    "date": "2025-04-18T03:26:25.000Z"
  },
  {
    "owner": "Harrisonthow",
    "repo": "akkaya-lab",
    "date": "2022-11-01T18:40:07.000Z"
  },
  {
    "owner": "monkiravn",
    "repo": "selab",
    "date": "2021-07-13T15:04:25.000Z"
  },
  {
    "owner": "IMASOFA-TL",
    "repo": "imasofa-tl.github.io",
    "date": "2023-10-26T03:43:50.000Z"
  },
  {
    "owner": "WUST-RM",
    "repo": "wust_chongshi_website",
    "date": "2025-08-11T08:48:31.000Z"
  },
  {
    "owner": "huapu-kaf",
    "repo": "GXU-RM-website",
    "date": "2025-03-28T02:39:23.000Z"
  },
  {
    "owner": "molecularmodelinglab",
    "repo": "molecularmodelinglab.github.io",
    "date": "2022-12-17T05:15:21.000Z"
  },
  {
    "owner": "caraml-lab",
    "repo": "caraml-lab",
    "date": "2021-08-03T21:26:02.000Z"
  },
  {
    "owner": "batmen-lab",
    "repo": "batmen-lab.github.io",
    "date": "2022-05-30T06:04:52.000Z"
  },
  {
    "owner": "Gidntsquia",
    "repo": "Outdated_ReZoom_Lab_website_template",
    "date": "2023-06-07T20:01:44.000Z"
  },
  {
    "owner": "geohai",
    "repo": "geohai-website",
    "date": "2023-10-26T18:24:38.000Z"
  },
  {
    "owner": "Architectural-Artificial-Intelligence",
    "repo": "aairl-lab-website",
    "date": "2021-08-14T20:46:21.000Z"
  },
  {
    "owner": "HeartAILab",
    "repo": "heartailab.github.io",
    "date": "2021-08-14T20:46:21.000Z"
  },
  {
    "owner": "yuuwang0204",
    "repo": "Guo-Lab-Tryouts",
    "date": "2023-09-25T20:50:21.000Z"
  },
  {
    "owner": "chentao9330",
    "repo": "aaa",
    "date": "2024-01-15T14:27:38.000Z"
  },
  {
    "owner": "binny1446",
    "repo": "SPC_Website",
    "date": "2023-07-08T13:35:02.000Z"
  },
  {
    "owner": "MysoreSparrow",
    "repo": "AGHornefLab",
    "date": "2023-07-28T14:02:01.000Z"
  },
  {
    "owner": "ply2022",
    "repo": "brawner_lab_UF",
    "date": "2023-08-25T02:22:44.000Z"
  },
  {
    "owner": "rachelcoyte",
    "repo": "rachelcoyte",
    "date": "2023-12-06T18:17:12.000Z"
  },
  {
    "owner": "U-AIM-SW-STARLab",
    "repo": "website",
    "date": "2023-12-12T11:43:31.000Z"
  },
  {
    "owner": "UniQuizzCloud",
    "repo": "SchoolSale",
    "date": "2024-01-24T21:28:11.000Z"
  },
  {
    "owner": "Hackfreedom888",
    "repo": "okweb",
    "date": "2023-09-03T04:03:06.000Z"
  },
  {
    "owner": "yuuwang0204",
    "repo": "guolabtryouts",
    "date": "2023-09-25T21:20:58.000Z"
  },
  {
    "owner": "dynsustech",
    "repo": "dyns5",
    "date": "2023-09-03T08:32:23.000Z"
  },
  {
    "owner": "Inverseit",
    "repo": "nsl-lab",
    "date": "2023-08-08T21:50:16.000Z"
  },
  {
    "owner": "Launinho",
    "repo": "Lab",
    "date": "2023-05-27T03:41:42.000Z"
  },
  {
    "owner": "snlab-hyu",
    "repo": "snlab",
    "date": "2023-06-05T09:02:25.000Z"
  },
  {
    "owner": "Ganeshkumar2104",
    "repo": "pb-lab.github.io",
    "date": "2023-04-18T14:44:14.000Z"
  },
  {
    "owner": "Qi-X-Lab",
    "repo": "qixlab",
    "date": "2023-03-23T09:12:52.000Z"
  },
  {
    "owner": "BrettIBell",
    "repo": "test",
    "date": "2024-04-18T18:43:39.000Z"
  },
  {
    "owner": "Amadei-Laboratory",
    "repo": "AmadeiLabWebsite",
    "date": "2024-03-22T15:45:22.000Z"
  },
  {
    "owner": "MichaelXinyuanZhang",
    "repo": "TESTPAGE.github.io",
    "date": "2024-04-22T13:09:36.000Z"
  },
  {
    "owner": "shu4dev",
    "repo": "NewACM",
    "date": "2024-03-09T10:28:54.000Z"
  },
  {
    "owner": "msafari18",
    "repo": "KariGenomicsLab.github.io",
    "date": "2024-03-08T21:37:49.000Z"
  },
  {
    "owner": "ankitsharmaMCET",
    "repo": "testweb",
    "date": "2024-05-10T07:48:09.000Z"
  },
  {
    "owner": "ConeonaChair",
    "repo": "ConeonaChair.github.io",
    "date": "2024-05-14T13:44:40.000Z"
  },
  {
    "owner": "BenzeneAvenger",
    "repo": "Test-Page",
    "date": "2024-05-02T18:29:33.000Z"
  },
  {
    "owner": "penterlab",
    "repo": "penterlab-website",
    "date": "2023-05-29T12:40:54.000Z"
  },
  {
    "owner": "GenomasSUS",
    "repo": "GenomasSUS.github.io",
    "date": "2024-04-22T19:52:51.000Z"
  },
  {
    "owner": "liebelab",
    "repo": "liebelab.github.io",
    "date": "2024-07-26T20:23:04.000Z"
  },
  {
    "owner": "calgo-lab",
    "repo": "calgo-lab.github.io",
    "date": "2024-09-14T10:04:13.000Z"
  },
  {
    "owner": "cvlg-njust",
    "repo": "cvlg-njust.github.io",
    "date": "2024-07-16T12:30:40.000Z"
  },
  {
    "owner": "trevonbadloeKUS",
    "repo": "metai",
    "date": "2024-08-14T18:27:53.000Z"
  },
  {
    "owner": "SMARTbiomed",
    "repo": "SMARTBiomed",
    "date": "2024-04-25T08:49:24.000Z"
  },
  {
    "owner": "PeerLabAI",
    "repo": "peerlab",
    "date": "2025-05-02T21:27:03.000Z"
  },
  {
    "owner": "SalivaryCommunication",
    "repo": "Jasmer_Lab_Website_2",
    "date": "2025-02-10T17:07:58.000Z"
  },
  {
    "owner": "aqzas",
    "repo": "labhmoe",
    "date": "2024-09-08T08:42:52.000Z"
  },
  {
    "owner": "ScienceInfor",
    "repo": "test",
    "date": "2025-07-17T09:27:28.000Z"
  },
  {
    "owner": "biomodsquad",
    "repo": "biomodsquad.github.io",
    "date": "2023-05-16T18:27:03.000Z"
  },
  {
    "owner": "sifrimlab",
    "repo": "sifrimlab.github.io",
    "date": "2024-02-14T14:23:55.000Z"
  },
  {
    "owner": "HarmGriffioen",
    "repo": "DelftTILab",
    "date": "2025-06-04T15:59:24.000Z"
  },
  {
    "owner": "nietianzong",
    "repo": "313lab",
    "date": "2024-11-07T12:47:04.000Z"
  },
  {
    "owner": "suyunlei",
    "repo": "UMS",
    "date": "2025-05-29T16:06:21.000Z"
  },
  {
    "owner": "CindyGTang",
    "repo": "AOEL",
    "date": "2025-06-25T02:43:35.000Z"
  },
  {
    "owner": "BCCHVisionLab",
    "repo": "bcchvisionlab.github.io",
    "date": "2024-09-09T21:15:42.000Z"
  },
  {
    "owner": "WooHyuna",
    "repo": "cyber-hydrology2.github.io",
    "date": "2025-01-07T04:53:48.000Z"
  },
  {
    "owner": "JustSustainabilityDesign",
    "repo": "JSD-website",
    "date": "2023-09-15T22:41:30.000Z"
  },
  {
    "owner": "snaqvi1990",
    "repo": "naqvilab",
    "date": "2023-10-27T00:22:06.000Z"
  },
  {
    "owner": "hegazylab",
    "repo": "labsite",
    "date": "2023-09-11T20:12:34.000Z"
  },
  {
    "owner": "IAIOnline",
    "repo": "iaionline.github.io",
    "date": "2025-01-22T09:52:43.000Z"
  },
  {
    "owner": "ldinis1",
    "repo": "Priggelab",
    "date": "2024-11-04T01:31:40.000Z"
  },
  {
    "owner": "lafinj",
    "repo": "strandlab-website",
    "date": "2025-07-01T16:48:13.000Z"
  },
  {
    "owner": "nexgem25",
    "repo": "nexgem",
    "date": "2023-03-26T05:37:36.000Z"
  },
  {
    "owner": "y1fanyang",
    "repo": "yifanlab",
    "date": "2025-07-18T09:33:30.000Z"
  },
  {
    "owner": "anajcaetano",
    "repo": "Caetano-lab",
    "date": "2021-08-14T20:46:21.000Z"
  },
  {
    "owner": "RobbenLab",
    "repo": "robben-lab-website",
    "date": "2023-08-23T03:15:33.000Z"
  },
  {
    "owner": "JinLabBioinfo",
    "repo": "lilabwebsite",
    "date": "2024-11-01T20:05:39.000Z"
  },
  {
    "owner": "GuhaLab",
    "repo": "guhalab.github.io",
    "date": "2024-03-03T18:00:27.000Z"
  },
  {
    "owner": "MJDelas",
    "repo": "delas-lab-website",
    "date": "2023-11-04T11:35:07.000Z"
  },
  {
    "owner": "hbeale",
    "repo": "website",
    "date": "2023-10-12T16:15:58.000Z"
  },
  {
    "owner": "TimSkvortsov",
    "repo": "skvortsov-lab-website",
    "date": "2021-08-14T20:46:21.000Z"
  },
  {
    "owner": "zuccminglab",
    "repo": "zucc-ming-lab",
    "date": "2023-05-17T05:31:02.000Z"
  },
  {
    "owner": "yuzutao1990",
    "repo": "yuzutao1990test.github.io",
    "date": "2025-02-20T00:13:00.000Z"
  },
  {
    "owner": "canzarlab",
    "repo": "lab-website",
    "date": "2023-05-20T18:46:55.000Z"
  },
  {
    "owner": "pbandjanet",
    "repo": "song-lab-website",
    "date": "2024-06-02T21:25:53.000Z"
  },
  {
    "owner": "xhosaa",
    "repo": "bit_brilliant",
    "date": "2025-03-25T14:28:21.000Z"
  },
  {
    "owner": "theZhuLab",
    "repo": "Zhu-Lab",
    "date": "2025-04-02T18:35:42.000Z"
  },
  {
    "owner": "zyang2k",
    "repo": "ScordLab",
    "date": "2024-05-08T19:41:58.000Z"
  },
  {
    "owner": "ExplainableMachines",
    "repo": "group_website",
    "date": "2024-02-20T12:27:25.000Z"
  },
  {
    "owner": "hostviewer",
    "repo": "inteqx-website",
    "date": "2023-08-14T03:28:17.000Z"
  },
  {
    "owner": "JinLabBioinfo",
    "repo": "jinlabwebsite",
    "date": "2024-10-30T18:16:37.000Z"
  },
  {
    "owner": "BurgessLab",
    "repo": "BurgessLab",
    "date": "2023-12-25T18:24:12.000Z"
  },
  {
    "owner": "lonelu",
    "repo": "lonelu.github.io",
    "date": "2021-08-14T20:46:21.000Z"
  },
  {
    "owner": "HershbergerLab",
    "repo": "HershLab.org",
    "date": "2021-08-14T20:46:21.000Z"
  },
  {
    "owner": "maypoleflyn",
    "repo": "SaladLab",
    "date": "2023-11-23T05:26:48.000Z"
  },
  {
    "owner": "yuzutao1990",
    "repo": "yucleiclab.github.io",
    "date": "2025-02-21T20:27:00.000Z"
  },
  {
    "owner": "SakaizaRajery",
    "repo": "sakaiza-website",
    "date": "2024-12-27T15:38:39.000Z"
  },
  {
    "owner": "TLILegume",
    "repo": "PerennialLegumes",
    "date": "2023-11-27T20:20:21.000Z"
  },
  {
    "owner": "rohsequ",
    "repo": "netpd-lab-site",
    "date": "2025-02-05T23:48:40.000Z"
  },
  {
    "owner": "a2g1n",
    "repo": "parafugelabwebsite",
    "date": "2024-11-24T12:27:43.000Z"
  },
  {
    "owner": "huhjina",
    "repo": "h2",
    "date": "2024-11-06T21:26:04.000Z"
  },
  {
    "owner": "marchion",
    "repo": "marchionniLab",
    "date": "2025-02-12T21:54:26.000Z"
  },
  {
    "owner": "TurnerLaboratory",
    "repo": "TurnerLaboratory.github.io",
    "date": "2023-07-12T03:36:38.000Z"
  },
  {
    "owner": "dwilliamsLab",
    "repo": "dwilliams-lab-website",
    "date": "2024-03-20T18:48:14.000Z"
  },
  {
    "owner": "Dftevn",
    "repo": "dftevn-website",
    "date": "2024-02-25T15:21:30.000Z"
  },
  {
    "owner": "wxyzed",
    "repo": "site",
    "date": "2023-05-17T20:49:19.000Z"
  },
  {
    "owner": "tvanlaar",
    "repo": "tvanlaar.github.io",
    "date": "2023-12-21T02:04:31.000Z"
  },
  {
    "owner": "ecamacho90",
    "repo": "CamachoAguilarLab-Website",
    "date": "2024-03-06T15:09:47.000Z"
  },
  {
    "owner": "DepledgeLab",
    "repo": "depledgelab.github.io",
    "date": "2025-01-06T14:32:56.000Z"
  },
  {
    "owner": "JieunSong",
    "repo": "speechandmindlab.github.io",
    "date": "2023-07-28T07:59:00.000Z"
  },
  {
    "owner": "MichaelJONeill",
    "repo": "michaeljoneill.github.io",
    "date": "2023-06-07T15:43:51.000Z"
  },
  {
    "owner": "vincentchemistry",
    "repo": "vincentchemistry.github.io",
    "date": "2025-07-15T14:30:07.000Z"
  },
  {
    "owner": "neuralizelab",
    "repo": "neuralizelab.github.io",
    "date": "2023-12-09T20:06:28.000Z"
  },
  {
    "owner": "ZhichaoXu",
    "repo": "XuLab_Repo",
    "date": "2024-09-09T17:39:23.000Z"
  },
  {
    "owner": "ericnatsmith",
    "repo": "LabINVITE",
    "date": "2024-02-17T05:13:35.000Z"
  },
  {
    "owner": "McBethLab",
    "repo": "mcbethlab.github.io",
    "date": "2024-02-17T19:47:42.000Z"
  },
  {
    "owner": "andrewdhawan",
    "repo": "tabula-rasa-website",
    "date": "2023-06-10T02:07:10.000Z"
  },
  {
    "owner": "labjte",
    "repo": "labjte.github.io",
    "date": "2023-05-05T06:13:13.000Z"
  },
  {
    "owner": "dolo",
    "repo": "dolo.github.io",
    "date": "2025-02-17T00:59:39.000Z"
  },
  {
    "owner": "colquittlab",
    "repo": "colquittlabsite",
    "date": "2024-11-15T04:57:20.000Z"
  },
  {
    "owner": "ajschulz",
    "repo": "ajschulz.github.io",
    "date": "2025-06-25T22:47:55.000Z"
  },
  {
    "owner": "crolllab",
    "repo": "crolllab_v3",
    "date": "2023-05-01T21:00:18.000Z"
  },
  {
    "owner": "CliMet",
    "repo": "CliMet.github.io",
    "date": "2023-08-02T09:12:21.000Z"
  },
  {
    "owner": "CarolineWBeck",
    "repo": "CarolineWBeck.github.io",
    "date": "2024-01-05T01:05:05.000Z"
  },
  {
    "owner": "lizmandeville",
    "repo": "lizmandeville.github.io",
    "date": "2025-07-18T19:48:22.000Z"
  },
  {
    "owner": "kaschak",
    "repo": "kaschak.github.io",
    "date": "2025-02-22T04:47:45.000Z"
  },
  {
    "owner": "donkerdude",
    "repo": "donkerdude.github.io",
    "date": "2023-12-11T18:40:15.000Z"
  },
  {
    "owner": "colquittlab",
    "repo": "colquittlab.github.io",
    "date": "2021-08-14T20:46:21.000Z"
  },
  {
    "owner": "bioticaresearchgroup",
    "repo": "bioticaresearchgroup.github.io",
    "date": "2023-09-02T06:08:08.000Z"
  },
  {
    "owner": "palomarlab",
    "repo": "palomarlab.github.io",
    "date": "2023-05-31T02:25:30.000Z"
  },
  {
    "owner": "dynsustech",
    "repo": "dynsustech.github.io",
    "date": "2023-09-07T10:48:34.000Z"
  },
  {
    "owner": "ICArmenian-Mycologists",
    "repo": "ICArmenian-Mycologists.github.io-v2",
    "date": "2023-05-05T22:16:25.000Z"
  },
  {
    "owner": "oceancascades",
    "repo": "oceancascades.github.io",
    "date": "2021-08-14T20:46:21.000Z"
  },
  {
    "owner": "amadeiglab",
    "repo": "AmadeiGLab.github.io",
    "date": "2024-03-22T16:00:10.000Z"
  },
  {
    "owner": "cosilab",
    "repo": "cosilab.github.io",
    "date": "2025-07-29T10:21:58.000Z"
  },
  {
    "owner": "benstemon",
    "repo": "benstemon.github.io",
    "date": "2024-07-05T16:36:55.000Z"
  },
  {
    "owner": "MathCancer",
    "repo": "mathcancer.github.io",
    "date": "2024-12-01T15:33:25.000Z"
  },
  {
    "owner": "horlbeck-lab",
    "repo": "horlbeck-lab-website",
    "date": "2025-05-27T02:49:45.000Z"
  },
  {
    "owner": "LaurelineLogiaco",
    "repo": "lab_compneuroCUAnschutz",
    "date": "2025-06-06T17:32:22.000Z"
  },
  {
    "owner": "CFMHMC",
    "repo": "CFMHMC.github.io",
    "date": "2024-02-17T01:04:40.000Z"
  },
  {
    "owner": "jpd119",
    "repo": "jpd119.github.io",
    "date": "2025-04-07T11:54:46.000Z"
  },
  {
    "owner": "VasudevanLab",
    "repo": "VasudevanLab.github.io",
    "date": "2025-04-14T02:38:01.000Z"
  },
  {
    "owner": "ankithvarun",
    "repo": "basil-website",
    "date": "2025-03-27T18:03:53.000Z"
  },
  {
    "owner": "HoangDangers",
    "repo": "energystoragelab123",
    "date": "2025-08-02T15:18:30.000Z"
  },
  {
    "owner": "margoemont",
    "repo": "margoemont.github.io",
    "date": "2023-08-24T14:29:42.000Z"
  },
  {
    "owner": "KachuriLab",
    "repo": "kachurilab.github.io",
    "date": "2023-09-18T22:16:42.000Z"
  },
  {
    "owner": "KwasekLab",
    "repo": "LabWebsiteTest",
    "date": "2024-07-20T00:08:56.000Z"
  },
  {
    "owner": "fundamentalvision",
    "repo": "fundamentalvision.github.io",
    "date": "2023-09-06T02:49:03.000Z"
  },
  {
    "owner": "doctor-12th",
    "repo": "lab-webseite",
    "date": "2025-05-08T15:22:33.000Z"
  },
  {
    "owner": "houlahanlab",
    "repo": "houlahanlab.github.io",
    "date": "2024-07-16T13:47:45.000Z"
  },
  {
    "owner": "sinclab",
    "repo": "sinclab.github.io",
    "date": "2025-01-22T17:36:21.000Z"
  },
  {
    "owner": "criifusion",
    "repo": "criifusion.github.io",
    "date": "2025-08-01T03:34:47.000Z"
  },
  {
    "owner": "markravinet",
    "repo": "markravinet.github.io",
    "date": "2024-01-25T11:48:51.000Z"
  },
  {
    "owner": "evancornett",
    "repo": "cornettlab",
    "date": "2024-05-16T04:05:06.000Z"
  },
  {
    "owner": "CreggLab",
    "repo": "CreggLab.github.io",
    "date": "2024-01-22T15:59:48.000Z"
  },
  {
    "owner": "skinimageanalysis",
    "repo": "skinimageanalysis.github.io",
    "date": "2024-11-25T05:24:54.000Z"
  },
  {
    "owner": "ZHCuiLab",
    "repo": "zhcuilab.github.io",
    "date": "2024-11-15T02:33:45.000Z"
  },
  {
    "owner": "SHSE4SML",
    "repo": "SHSE4SML.github.io",
    "date": "2023-09-15T20:33:24.000Z"
  },
  {
    "owner": "NEXGEM",
    "repo": "nexgem.github.io",
    "date": "2023-03-26T08:20:00.000Z"
  },
  {
    "owner": "teamgrossen",
    "repo": "website",
    "date": "2023-06-03T22:33:20.000Z"
  },
  {
    "owner": "YunlongLiuLab",
    "repo": "YunlongLiuLab.github.io",
    "date": "2024-02-09T15:39:43.000Z"
  },
  {
    "owner": "ciencialatitud0",
    "repo": "ciencialatitud0.github.io",
    "date": "2023-05-16T22:41:38.000Z"
  },
  {
    "owner": "fsotoc",
    "repo": "ccnlab-website",
    "date": "2025-01-16T05:27:10.000Z"
  },
  {
    "owner": "hamidrezaHemati",
    "repo": "hamidrezahemati.github.io",
    "date": "2025-07-20T11:50:40.000Z"
  },
  {
    "owner": "RupleenK",
    "repo": "Lab-Website",
    "date": "2024-06-04T22:07:30.000Z"
  },
  {
    "owner": "netpd",
    "repo": "netpd.github.io",
    "date": "2025-02-11T00:34:56.000Z"
  },
  {
    "owner": "sunericd",
    "repo": "sunlab",
    "date": "2025-07-04T23:37:38.000Z"
  },
  {
    "owner": "I-UESTC",
    "repo": "I-UESTC.github.io",
    "date": "2024-11-15T09:02:09.000Z"
  },
  {
    "owner": "marchetto-lab",
    "repo": "marchetto-lab.github.io",
    "date": "2024-09-13T15:17:14.000Z"
  },
  {
    "owner": "pml4sc",
    "repo": "pml4sc.github.io",
    "date": "2025-07-01T22:14:20.000Z"
  },
  {
    "owner": "mphowardlab",
    "repo": "mphowardlab.github.io",
    "date": "2023-03-15T23:25:29.000Z"
  },
  {
    "owner": "goeckslab",
    "repo": "lab-website",
    "date": "2023-08-16T17:59:42.000Z"
  },
  {
    "owner": "bmeiilab",
    "repo": "bmeiilab.github.io",
    "date": "2025-08-07T07:12:02.000Z"
  },
  {
    "owner": "guanlii",
    "repo": "guanlii.github.io",
    "date": "2025-07-20T08:27:48.000Z"
  },
  {
    "owner": "FiskLab",
    "repo": "FiskLab.github.io",
    "date": "2023-09-11T18:49:04.000Z"
  },
  {
    "owner": "dgucps",
    "repo": "dgucps.github.io",
    "date": "2023-02-27T23:04:24.000Z"
  },
  {
    "owner": "FrankDubois",
    "repo": "duboislab",
    "date": "2023-10-08T11:09:35.000Z"
  },
  {
    "owner": "cucumber-potato",
    "repo": "Research-_template1",
    "date": "2024-07-11T09:02:26.000Z"
  },
  {
    "owner": "AISPRG",
    "repo": "AISP-Lab",
    "date": "2024-10-15T23:30:44.000Z"
  },
  {
    "owner": "DeltaGBio",
    "repo": "DeltaGBio.github.io",
    "date": "2025-05-09T19:42:35.000Z"
  },
  {
    "owner": "cstl-kaist",
    "repo": "cstl-website",
    "date": "2024-02-21T07:46:15.000Z"
  },
  {
    "owner": "HSA4ESMLS",
    "repo": "HSA4ESMLS.github.io",
    "date": "2023-09-15T19:24:17.000Z"
  },
  {
    "owner": "rlaplaza",
    "repo": "rlaplaza.github.io",
    "date": "2025-07-24T17:19:52.000Z"
  },
  {
    "owner": "nemelab",
    "repo": "nemelab.github.io",
    "date": "2025-04-16T06:57:00.000Z"
  },
  {
    "owner": "rcoyte",
    "repo": "rcoyte.github.io",
    "date": "2023-11-04T01:47:55.000Z"
  },
  {
    "owner": "lolaquraishi",
    "repo": "greenlab",
    "date": "2024-07-27T17:40:43.000Z"
  },
  {
    "owner": "UTSA-VIRLab",
    "repo": "UTSA-VIRLab.github.io",
    "date": "2024-12-22T18:57:27.000Z"
  },
  {
    "owner": "nobuaki-mzmt",
    "repo": "mizumoto-lab",
    "date": "2024-02-02T21:03:14.000Z"
  },
  {
    "owner": "370126",
    "repo": "gattaca",
    "date": "2025-03-11T02:30:46.000Z"
  },
  {
    "owner": "dagdpz",
    "repo": "dagdpz.github.io",
    "date": "2024-03-29T22:46:59.000Z"
  },
  {
    "owner": "wallematthias",
    "repo": "website",
    "date": "2025-06-13T15:08:42.000Z"
  },
  {
    "owner": "zerunniu",
    "repo": "lab-website-template",
    "date": "2025-08-02T04:43:46.000Z"
  },
  {
    "owner": "sharifisl",
    "repo": "gaslabsharif",
    "date": "2025-05-26T09:49:58.000Z"
  },
  {
    "owner": "GeoXAI",
    "repo": "GeoXAI",
    "date": "2024-11-16T19:08:00.000Z"
  },
  {
    "owner": "vermaaslab",
    "repo": "websiteupdate",
    "date": "2025-07-07T01:35:31.000Z"
  },
  {
    "owner": "Robovisionlab",
    "repo": "robovisionlab",
    "date": "2025-02-03T19:19:08.000Z"
  },
  {
    "owner": "AgrawalAmey",
    "repo": "gatech-sysml",
    "date": "2024-03-10T04:08:06.000Z"
  },
  {
    "owner": "harvard-embodied-intelligence",
    "repo": "harvard-embodied-intelligence.github.io",
    "date": "2021-08-14T20:46:21.000Z"
  },
  {
    "owner": "saramathieson",
    "repo": "lab",
    "date": "2025-07-04T10:52:11.000Z"
  },
  {
    "owner": "aamickle",
    "repo": "Micklelab",
    "date": "2025-07-29T00:33:26.000Z"
  },
  {
    "owner": "pultoW",
    "repo": "mylab",
    "date": "2023-08-23T09:06:33.000Z"
  },
  {
    "owner": "HocherLab",
    "repo": "Labwebsite",
    "date": "2025-04-11T09:04:30.000Z"
  },
  {
    "owner": "ICARUS-Lab-Psych",
    "repo": "icarus",
    "date": "2023-03-24T23:06:21.000Z"
  },
  {
    "owner": "hunglongtrangithub",
    "repo": "LAILab",
    "date": "2023-03-05T17:00:32.000Z"
  },
  {
    "owner": "rokitalab",
    "repo": "rokitalab.com",
    "date": "2021-08-14T20:46:21.000Z"
  },
  {
    "owner": "siva5",
    "repo": "PaQGenLabWebsite",
    "date": "2025-01-21T07:20:23.000Z"
  },
  {
    "owner": "ptitle",
    "repo": "macroEEB",
    "date": "2025-02-15T20:57:58.000Z"
  },
  {
    "owner": "theMontilab",
    "repo": "theMontilab",
    "date": "2025-04-21T11:45:20.000Z"
  },
  {
    "owner": "sorrymaker03",
    "repo": "labwebsite",
    "date": "2025-04-10T18:59:43.000Z"
  },
  {
    "owner": "sangb21",
    "repo": "testsite",
    "date": "2024-01-03T20:04:04.000Z"
  },
  {
    "owner": "flicklab",
    "repo": "flicklab",
    "date": "2023-03-01T17:10:46.000Z"
  },
  {
    "owner": "MartinGarlovsky",
    "repo": "MartinGarlovsky",
    "date": "2023-05-30T13:04:08.000Z"
  },
  {
    "owner": "dynsustech",
    "repo": "dyns6",
    "date": "2023-09-03T09:26:08.000Z"
  },
  {
    "owner": "MarymountUniversity",
    "repo": "maria",
    "date": "2025-07-18T17:15:49.000Z"
  },
  {
    "owner": "aiformedresearch",
    "repo": "aiformedresearch",
    "date": "2023-05-25T10:41:19.000Z"
  },
  {
    "owner": "yunchengluo",
    "repo": "CI-Lab-1",
    "date": "2025-07-02T11:36:58.000Z"
  },
  {
    "owner": "MOTIF-lab",
    "repo": "webpage",
    "date": "2024-08-23T20:50:42.000Z"
  },
  {
    "owner": "PartiLAB",
    "repo": "my_lab_website",
    "date": "2024-08-24T05:10:07.000Z"
  },
  {
    "owner": "Sachin-Gadani",
    "repo": "gadani-lab-website",
    "date": "2025-03-20T20:09:56.000Z"
  },
  {
    "owner": "carolineh12",
    "repo": "dphil",
    "date": "2024-03-09T02:58:45.000Z"
  },
  {
    "owner": "yemiadesina",
    "repo": "materialx",
    "date": "2023-09-12T17:46:38.000Z"
  },
  {
    "owner": "gabopemoy",
    "repo": "L-C-Lab",
    "date": "2024-10-27T18:05:14.000Z"
  },
  {
    "owner": "munschauerlab",
    "repo": "munschauer-lab-website",
    "date": "2024-05-28T16:15:36.000Z"
  },
  {
    "owner": "mathutopia",
    "repo": "dpluslab",
    "date": "2024-09-28T21:48:00.000Z"
  },
  {
    "owner": "Neboer",
    "repo": "GraphicsGroupLab",
    "date": "2025-01-06T03:13:25.000Z"
  },
  {
    "owner": "cuk-cvlab",
    "repo": "cuk-cvlab",
    "date": "2025-07-31T13:53:01.000Z"
  },
  {
    "owner": "zcapamh",
    "repo": "deanlab",
    "date": "2023-11-24T13:46:18.000Z"
  },
  {
    "owner": "mabausch",
    "repo": "AppliedNeuro",
    "date": "2024-02-10T11:32:44.000Z"
  },
  {
    "owner": "camp-lab-tud",
    "repo": "camp-lab-website",
    "date": "2025-07-18T09:18:01.000Z"
  },
  {
    "owner": "xtoazt",
    "repo": "rohanscams",
    "date": "2025-01-17T22:22:09.000Z"
  },
  {
    "owner": "ais-lab",
    "repo": "ais-lab.github.io",
    "date": "2025-01-23T14:30:03.000Z"
  },
  {
    "owner": "Stanislabski",
    "repo": "Stanislabski.github.io",
    "date": "2025-06-18T17:11:51.000Z"
  },
  {
    "owner": "CarolineWBeck",
    "repo": "Becklab",
    "date": "2024-01-06T08:16:21.000Z"
  },
  {
    "owner": "lsb53",
    "repo": "LoganBilletResearch",
    "date": "2025-02-16T20:31:11.000Z"
  },
  {
    "owner": "ntoulclab",
    "repo": "tttt",
    "date": "2024-01-25T05:22:48.000Z"
  },
  {
    "owner": "Sofie8",
    "repo": "VERTHY",
    "date": "2025-03-05T10:50:39.000Z"
  },
  {
    "owner": "alexpcheng",
    "repo": "pellanchenglab",
    "date": "2023-03-04T18:40:51.000Z"
  },
  {
    "owner": "ArihantTiwari",
    "repo": "SQuAD",
    "date": "2025-05-24T17:32:36.000Z"
  },
  {
    "owner": "Streit-C",
    "repo": "amd-lab-website",
    "date": "2024-12-05T00:50:07.000Z"
  },
  {
    "owner": "ozturkelif",
    "repo": "happybirthdayhocam",
    "date": "2023-05-12T14:24:49.000Z"
  },
  {
    "owner": "JingchuHu",
    "repo": "star.lab",
    "date": "2024-07-04T11:50:33.000Z"
  },
  {
    "owner": "Xuan356",
    "repo": "XuanLab",
    "date": "2025-02-21T16:52:29.000Z"
  },
  {
    "owner": "wwallent",
    "repo": "test",
    "date": "2024-08-05T20:22:42.000Z"
  },
  {
    "owner": "ivioletsss",
    "repo": "Huminex",
    "date": "2025-07-14T06:02:31.000Z"
  },
  {
    "owner": "sciai-lab",
    "repo": "lab-webpage",
    "date": "2023-10-30T10:48:17.000Z"
  },
  {
    "owner": "penmlab",
    "repo": "penmlab.github.io",
    "date": "2025-06-02T01:23:59.000Z"
  },
  {
    "owner": "sidelook778",
    "repo": "sorawa",
    "date": "2024-01-07T09:25:23.000Z"
  },
  {
    "owner": "lynalllab",
    "repo": "biomind-website",
    "date": "2025-05-05T13:57:58.000Z"
  },
  {
    "owner": "QuillanGee",
    "repo": "VRWalkingWebsite",
    "date": "2024-11-08T03:34:02.000Z"
  },
  {
    "owner": "ijayas",
    "repo": "signalling-nanodomains.org",
    "date": "2023-09-14T10:56:21.000Z"
  },
  {
    "owner": "evolinus",
    "repo": "zooe",
    "date": "2024-11-29T16:45:01.000Z"
  },
  {
    "owner": "Pvictox",
    "repo": "site_template",
    "date": "2024-10-08T13:20:44.000Z"
  },
  {
    "owner": "GabrielaFranca",
    "repo": "Lab-Website-Template",
    "date": "2025-08-01T21:36:51.000Z"
  },
  {
    "owner": "happypanda94",
    "repo": "wang-bits.github.io",
    "date": "2025-01-21T19:52:11.000Z"
  },
  {
    "owner": "kseskv",
    "repo": "DevEpi_Lab",
    "date": "2025-03-12T04:06:27.000Z"
  },
  {
    "owner": "jzheng20",
    "repo": "websit",
    "date": "2025-06-03T00:30:26.000Z"
  },
  {
    "owner": "GoudetGroup",
    "repo": "GoudetWebsite",
    "date": "2025-02-03T10:08:01.000Z"
  },
  {
    "owner": "FMRealLab",
    "repo": "website",
    "date": "2025-03-11T14:42:58.000Z"
  },
  {
    "owner": "LupianezLab",
    "repo": "Website",
    "date": "2025-03-31T13:37:44.000Z"
  },
  {
    "owner": "Tr33Bug",
    "repo": "testGreenLab",
    "date": "2025-05-14T15:02:00.000Z"
  },
  {
    "owner": "EmmaCarlson",
    "repo": "majewskilab",
    "date": "2025-01-15T15:47:46.000Z"
  },
  {
    "owner": "DeepTenLab",
    "repo": "DeepTenLab",
    "date": "2024-12-09T13:47:26.000Z"
  },
  {
    "owner": "cairo-lab",
    "repo": "lab-website",
    "date": "2024-12-03T23:57:42.000Z"
  },
  {
    "owner": "Allenscript",
    "repo": "lab",
    "date": "2024-10-30T03:03:14.000Z"
  },
  {
    "owner": "MarraLab",
    "repo": "marralab",
    "date": "2024-01-25T17:33:14.000Z"
  },
  {
    "owner": "physycom",
    "repo": "physycom.github.io",
    "date": "2025-02-04T13:36:54.000Z"
  },
  {
    "owner": "Llannelongue",
    "repo": "website-lannelongue-group",
    "date": "2025-01-06T20:48:39.000Z"
  },
  {
    "owner": "RM2214",
    "repo": "rm2214.github.io",
    "date": "2024-07-23T02:45:03.000Z"
  },
  {
    "owner": "ivioletsss",
    "repo": "lab",
    "date": "2025-07-10T13:52:37.000Z"
  },
  {
    "owner": "zerunniu",
    "repo": "webtest",
    "date": "2025-03-14T05:16:16.000Z"
  },
  {
    "owner": "BouriMohammed",
    "repo": "Machine-Learning-and-Control-Theory",
    "date": "2025-08-06T17:53:59.000Z"
  },
  {
    "owner": "kunmishra2599",
    "repo": "lab-website",
    "date": "2024-07-09T03:50:29.000Z"
  },
  {
    "owner": "kiraz-ai",
    "repo": "kiraz.ai",
    "date": "2025-05-27T17:17:28.000Z"
  },
  {
    "owner": "DHRUVvkdv",
    "repo": "lewas-lab-website",
    "date": "2024-12-25T01:19:16.000Z"
  },
  {
    "owner": "Faraday-R-Lab",
    "repo": "GEDP-LAB.github.io",
    "date": "2023-09-02T01:48:10.000Z"
  },
  {
    "owner": "yuzutao1990",
    "repo": "lab.github.io",
    "date": "2025-02-21T16:16:09.000Z"
  },
  {
    "owner": "Fangch-JKbai",
    "repo": "web",
    "date": "2021-08-14T20:46:21.000Z"
  },
  {
    "owner": "shear-lab",
    "repo": "shear-lab.github.io",
    "date": "2025-05-15T16:53:43.000Z"
  },
  {
    "owner": "changtvs",
    "repo": "intmedtechlab",
    "date": "2025-03-05T08:13:36.000Z"
  },
  {
    "owner": "mosaic-Wlab",
    "repo": "mosaic-Wlab.github.io",
    "date": "2025-01-23T21:39:40.000Z"
  },
  {
    "owner": "justen-saini",
    "repo": "LIMB-Lab.github.io",
    "date": "2025-07-24T15:31:05.000Z"
  },
  {
    "owner": "DagilisLab",
    "repo": "DagilisLab",
    "date": "2024-10-21T18:18:42.000Z"
  },
  {
    "owner": "KambohLab",
    "repo": "KambohLab",
    "date": "2025-03-07T21:12:06.000Z"
  },
  {
    "owner": "murrayds",
    "repo": "ockti-lab",
    "date": "2025-06-10T17:41:42.000Z"
  },
  {
    "owner": "regulatory-genomics",
    "repo": "regulatory-genomics.github.io",
    "date": "2021-08-14T20:46:21.000Z"
  },
  {
    "owner": "kindlab-ai",
    "repo": "kindlab-ai.github.io",
    "date": "2025-01-09T08:38:14.000Z"
  },
  {
    "owner": "ScienceInfor",
    "repo": "Little-Molecular1",
    "date": "2025-07-16T13:57:42.000Z"
  },
  {
    "owner": "yemiadesina",
    "repo": "website",
    "date": "2023-09-09T19:04:59.000Z"
  },
  {
    "owner": "bic-leelab",
    "repo": "bic-leelab-website",
    "date": "2025-02-04T08:38:58.000Z"
  },
  {
    "owner": "ZMonfared",
    "repo": "mylabwebsite",
    "date": "2024-10-05T20:38:34.000Z"
  },
  {
    "owner": "dianaroopchand",
    "repo": "dianaroopchandlabwebsite",
    "date": "2023-03-09T20:03:06.000Z"
  },
  {
    "owner": "BIGAI-ML",
    "repo": "BIGAI-ML.github.io",
    "date": "2021-08-14T20:46:21.000Z"
  },
  {
    "owner": "i-abr",
    "repo": "i-abr.github.io",
    "date": "2023-08-19T22:41:23.000Z"
  },
  {
    "owner": "jkaelber",
    "repo": "research",
    "date": "2023-04-05T01:03:54.000Z"
  },
  {
    "owner": "e-cavan",
    "repo": "cavanlab",
    "date": "2024-10-08T13:04:19.000Z"
  },
  {
    "owner": "Prototipagem-LabEAN-LNNano",
    "repo": "site-labean",
    "date": "2023-04-16T23:22:41.000Z"
  },
  {
    "owner": "Muthu-Jeyanthi",
    "repo": "c3n_temp",
    "date": "2024-07-14T09:20:55.000Z"
  },
  {
    "owner": "Konzie68",
    "repo": "Lab-GCC",
    "date": "2025-07-10T06:11:07.000Z"
  },
  {
    "owner": "tosulambdas",
    "repo": "Lambdas-Webpage-2.0",
    "date": "2023-11-20T00:53:56.000Z"
  },
  {
    "owner": "KerneyAn",
    "repo": "LabWebsite.github.io",
    "date": "2023-11-13T12:48:10.000Z"
  },
  {
    "owner": "katielavigne",
    "repo": "lab-website",
    "date": "2023-06-22T19:46:50.000Z"
  },
  {
    "owner": "yuyanchenglab",
    "repo": "yuyanchenglab.github.io",
    "date": "2024-10-15T15:45:27.000Z"
  },
  {
    "owner": "starry2048",
    "repo": "lab-website",
    "date": "2023-12-25T11:29:25.000Z"
  },
  {
    "owner": "lwathieu1",
    "repo": "lab-website",
    "date": "2023-10-24T20:26:15.000Z"
  },
  {
    "owner": "Havaili",
    "repo": "lab-website",
    "date": "2023-10-19T13:59:29.000Z"
  },
  {
    "owner": "pmquiros",
    "repo": "lab-website",
    "date": "2024-10-02T11:31:37.000Z"
  },
  {
    "owner": "ojosam25",
    "repo": "FUTA-ATMOSPHERIC-PHYSICS-GROUP",
    "date": "2025-03-28T12:52:56.000Z"
  },
  {
    "owner": "ScienceInfor",
    "repo": "test3",
    "date": "2025-07-17T13:00:08.000Z"
  },
  {
    "owner": "HoangDangers",
    "repo": "test1",
    "date": "2025-08-02T16:18:22.000Z"
  },
  {
    "owner": "hkruoft",
    "repo": "uoftsysnet",
    "date": "2024-10-04T21:39:12.000Z"
  },
  {
    "owner": "kaschak",
    "repo": "newtemp",
    "date": "2025-02-22T04:47:45.000Z"
  },
  {
    "owner": "kmjhyn",
    "repo": "website",
    "date": "2024-07-29T15:11:49.000Z"
  },
  {
    "owner": "QuantMarineEcoLab",
    "repo": "test",
    "date": "2025-02-25T20:11:29.000Z"
  },
  {
    "owner": "LaboratorioSperimentale",
    "repo": "seminari",
    "date": "2025-02-06T12:16:28.000Z"
  },
  {
    "owner": "S2O-datastandards",
    "repo": "s2o-datastandards.github.io",
    "date": "2025-02-26T19:48:02.000Z"
  },
  {
    "owner": "Project-OMA",
    "repo": "Project-OMA.github.io",
    "date": "2024-10-02T13:44:12.000Z"
  },
  {
    "owner": "feg-lab",
    "repo": "feg-lab.github.io",
    "date": "2024-11-23T11:24:24.000Z"
  },
  {
    "owner": "wfy3364",
    "repo": "website-template",
    "date": "2024-07-22T08:55:37.000Z"
  },
  {
    "owner": "jeudicode",
    "repo": "hormigas-new",
    "date": "2021-08-14T20:46:21.000Z"
  },
  {
    "owner": "smorad",
    "repo": "bolt-lab",
    "date": "2024-08-30T01:53:59.000Z"
  },
  {
    "owner": "FlorinNeuro",
    "repo": "FlorinNeuro.github.io",
    "date": "2024-08-28T21:49:15.000Z"
  },
  {
    "owner": "lonelu",
    "repo": "lulei",
    "date": "2025-07-18T07:33:05.000Z"
  },
  {
    "owner": "HoangDangers",
    "repo": "abc",
    "date": "2025-08-02T15:18:04.000Z"
  },
  {
    "owner": "Brsc11",
    "repo": "The-Steffen-Fuchs-Lab",
    "date": "2025-02-27T13:25:14.000Z"
  },
  {
    "owner": "ScienceInfor",
    "repo": "test4",
    "date": "2025-07-17T15:19:27.000Z"
  },
  {
    "owner": "m1ma0314",
    "repo": "salemlab-website-test",
    "date": "2024-01-27T22:05:15.000Z"
  },
  {
    "owner": "slbae",
    "repo": "HFXE-website",
    "date": "2024-11-15T05:06:59.000Z"
  },
  {
    "owner": "ZJU-IDEA",
    "repo": "ZJU-IDEA.github.io",
    "date": "2024-12-04T02:51:58.000Z"
  },
  {
    "owner": "Gidntsquia",
    "repo": "CDCL-website",
    "date": "2023-06-10T16:04:18.000Z"
  },
  {
    "owner": "lueckenlab",
    "repo": "org-website",
    "date": "2023-04-06T10:50:57.000Z"
  },
  {
    "owner": "ntoulclab",
    "repo": "ntou-lcl",
    "date": "2024-01-17T10:18:29.000Z"
  },
  {
    "owner": "saharzal",
    "repo": "test_lab_1",
    "date": "2025-03-03T08:11:40.000Z"
  },
  {
    "owner": "yq-qiu",
    "repo": "qiu-group-website",
    "date": "2025-02-05T20:24:52.000Z"
  },
  {
    "owner": "Germophile",
    "repo": "archia_wiki",
    "date": "2024-07-10T00:07:53.000Z"
  },
  {
    "owner": "ScienceInfor",
    "repo": "little",
    "date": "2025-07-18T07:32:00.000Z"
  },
  {
    "owner": "skittishgecko",
    "repo": "tetonhodl",
    "date": "2025-01-24T02:04:08.000Z"
  },
  {
    "owner": "ETAIC",
    "repo": "ETAICCC.github.io",
    "date": "2025-06-13T18:03:14.000Z"
  },
  {
    "owner": "Fangch-JKbai",
    "repo": "fang.github.io",
    "date": "2021-08-14T20:46:21.000Z"
  },
  {
    "owner": "Hamim-98-PT",
    "repo": "OpenMedTech",
    "date": "2025-05-05T15:53:17.000Z"
  },
  {
    "owner": "rs4cloud",
    "repo": "rs4cloud.github.io",
    "date": "2024-08-16T08:43:03.000Z"
  },
  {
    "owner": "EmmaCarlson",
    "repo": "majewski_lab",
    "date": "2024-11-22T21:58:39.000Z"
  },
  {
    "owner": "ENWEREM0DE",
    "repo": "rail-lab-website",
    "date": "2025-04-01T17:20:16.000Z"
  },
  {
    "owner": "PING-ResearchLab",
    "repo": "PING-ResearchLab.github.io_old",
    "date": "2025-06-19T15:12:40.000Z"
  },
  {
    "owner": "CRHudson",
    "repo": "CRHudson.github.io",
    "date": "2025-08-10T19:47:50.000Z"
  },
  {
    "owner": "komaba461",
    "repo": "komaba",
    "date": "2023-09-22T19:04:01.000Z"
  },
  {
    "owner": "vilab-koreatech",
    "repo": "vilab-koreatech.github.io",
    "date": "2024-11-16T10:17:32.000Z"
  },
  {
    "owner": "wanglab-unmc",
    "repo": "wanglab-unmc.github.io",
    "date": "2025-01-14T23:50:17.000Z"
  },
  {
    "owner": "skuttal",
    "repo": "HFXE",
    "date": "2024-11-15T05:43:58.000Z"
  },
  {
    "owner": "englertlab",
    "repo": "englert-lab",
    "date": "2023-05-17T19:05:40.000Z"
  },
  {
    "owner": "maxh768",
    "repo": "website-2",
    "date": "2025-04-07T15:38:02.000Z"
  },
  {
    "owner": "The-RIIPL-lab",
    "repo": "The-RIIPL-lab.github.io",
    "date": "2024-03-20T19:42:13.000Z"
  },
  {
    "owner": "sintia77b",
    "repo": "lsangarita",
    "date": "2024-06-25T20:28:33.000Z"
  },
  {
    "owner": "hatelikeit",
    "repo": "Fruits",
    "date": "2025-03-03T22:37:11.000Z"
  },
  {
    "owner": "manguyen0017",
    "repo": "template-test",
    "date": "2025-06-18T23:38:36.000Z"
  },
  {
    "owner": "wu-tecon",
    "repo": "wu-tecon.github.io",
    "date": "2024-03-26T11:47:47.000Z"
  },
  {
    "owner": "nietianzong",
    "repo": "313lab-qdu",
    "date": "2024-11-07T13:15:18.000Z"
  },
  {
    "owner": "kbartol02",
    "repo": "Pearce-Lab",
    "date": "2025-02-03T16:57:40.000Z"
  },
  {
    "owner": "Starlitnightly",
    "repo": "bio_lab",
    "date": "2023-08-29T22:55:16.000Z"
  },
  {
    "owner": "shervinsafavi",
    "repo": "cmclab",
    "date": "2023-10-18T19:48:35.000Z"
  },
  {
    "owner": "integrativemicrobiomesciences-lab",
    "repo": "integrativemicrobiomesciences-lab.github.io",
    "date": "2025-03-10T22:00:19.000Z"
  },
  {
    "owner": "airlabmonash",
    "repo": "airlab-website",
    "date": "2023-05-31T00:06:52.000Z"
  },
  {
    "owner": "kdunlop",
    "repo": "Dunlop_Lab",
    "date": "2024-12-02T14:58:34.000Z"
  },
  {
    "owner": "dhawale-lab",
    "repo": "dhawale-lab.github.io",
    "date": "2021-08-14T20:46:21.000Z"
  },
  {
    "owner": "id-urbanlabs",
    "repo": "id-urbanlabs.github.io",
    "date": "2025-05-01T02:47:54.000Z"
  },
  {
    "owner": "PING-ResearchLab",
    "repo": "ping-researchlab.github.io",
    "date": "2025-06-19T15:30:49.000Z"
  },
  {
    "owner": "herptilemicrobiomes",
    "repo": "herptilemicrobiomes.github.io",
    "date": "2021-08-14T20:46:21.000Z"
  },
  {
    "owner": "c2vn",
    "repo": "Cardano-Blockchain-Lab",
    "date": "2024-06-05T04:02:17.000Z"
  },
  {
    "owner": "lsh-cn",
    "repo": "lsh-cn2.github.io",
    "date": "2024-11-20T02:43:45.000Z"
  },
  {
    "owner": "dohuuphu",
    "repo": "ACM_website",
    "date": "2024-12-03T06:29:00.000Z"
  },
  {
    "owner": "glmsr12",
    "repo": "lab-website-main",
    "date": "2023-05-01T18:17:56.000Z"
  },
  {
    "owner": "iros1231",
    "repo": "iros1231.github.io",
    "date": "2024-01-06T06:11:58.000Z"
  },
  {
    "owner": "zsysgdsz",
    "repo": "zhang-lab",
    "date": "2025-07-09T21:54:30.000Z"
  },
  {
    "owner": "vcl-ln",
    "repo": "vcl-ln.github.io",
    "date": "2024-02-20T04:01:38.000Z"
  },
  {
    "owner": "inha-cnlab",
    "repo": "inha-cnlab.github.io",
    "date": "2023-11-21T07:07:47.000Z"
  },
  {
    "owner": "health-interoperability-lab",
    "repo": "site",
    "date": "2023-10-04T17:53:20.000Z"
  },
  {
    "owner": "Harrisonthow",
    "repo": "lambdas-osu",
    "date": "2023-06-28T19:46:39.000Z"
  },
  {
    "owner": "Jokerealm",
    "repo": "LabWebsites",
    "date": "2024-08-14T06:44:24.000Z"
  },
  {
    "owner": "DnA-FX",
    "repo": "DnA-FX.github.io",
    "date": "2025-04-03T21:05:39.000Z"
  },
  {
    "owner": "brennan-research",
    "repo": "brennan-research.github.io",
    "date": "2023-06-13T17:02:45.000Z"
  },
  {
    "owner": "emrysguo",
    "repo": "lab_website",
    "date": "2024-01-08T21:59:16.000Z"
  },
  {
    "owner": "inspire-research",
    "repo": "inspire-research.github.io",
    "date": "2024-11-26T17:26:26.000Z"
  },
  {
    "owner": "HILMR",
    "repo": "CASIA-FCL",
    "date": "2025-01-15T06:43:37.000Z"
  },
  {
    "owner": "Hongyun-Liu",
    "repo": "Hongyun-Liu.github.io",
    "date": "2025-05-21T07:51:24.000Z"
  },
  {
    "owner": "TiYooY",
    "repo": "Lab-site",
    "date": "2025-08-10T16:18:50.000Z"
  },
  {
    "owner": "songroup",
    "repo": "sonlab-website",
    "date": "2024-07-15T12:37:03.000Z"
  },
  {
    "owner": "CGK-Laboratory",
    "repo": "CGK-Laboratory.github.io",
    "date": "2024-09-07T23:35:44.000Z"
  },
  {
    "owner": "ivioletsss",
    "repo": "lab_website",
    "date": "2025-07-10T09:46:03.000Z"
  },
  {
    "owner": "csed-help-seeking",
    "repo": "csed-help-seeking",
    "date": "2024-08-06T03:53:39.000Z"
  },
  {
    "owner": "friedchickean",
    "repo": "template-test",
    "date": "2024-12-11T18:21:58.000Z"
  },
  {
    "owner": "AndyPawn",
    "repo": "polyu-taslab.github.io",
    "date": "2024-12-06T04:22:44.000Z"
  },
  {
    "owner": "flexcom-tech",
    "repo": "flexcom-tech.github.io",
    "date": "2025-01-27T04:48:04.000Z"
  },
  {
    "owner": "Keeganlt",
    "repo": "Keeganlt.github.io",
    "date": "2023-11-13T00:04:11.000Z"
  },
  {
    "owner": "rcastellsg",
    "repo": "roger.castellsgraells",
    "date": "2023-04-27T01:39:43.000Z"
  },
  {
    "owner": "obaralab",
    "repo": "LabWebsite",
    "date": "2024-09-03T23:53:41.000Z"
  },
  {
    "owner": "mkarimi53",
    "repo": "bcolab-website",
    "date": "2024-11-02T13:30:34.000Z"
  },
  {
    "owner": "kavi10",
    "repo": "kannan-lab",
    "date": "2025-01-06T05:14:37.000Z"
  },
  {
    "owner": "ININ-Drops",
    "repo": "ININ-Drops.github.io",
    "date": "2024-11-22T04:07:26.000Z"
  },
  {
    "owner": "foundjem",
    "repo": "inSeco",
    "date": "2025-02-21T17:17:49.000Z"
  },
  {
    "owner": "JingboMeng",
    "repo": "Communication-and-Computation-Lab",
    "date": "2025-04-07T17:17:44.000Z"
  },
  {
    "owner": "Ethanwithaheart",
    "repo": "Lab",
    "date": "2024-10-14T14:14:47.000Z"
  },
  {
    "owner": "IDImmune",
    "repo": "lab",
    "date": "2025-06-27T00:33:10.000Z"
  },
  {
    "owner": "StefanSander3",
    "repo": "lab-webpage",
    "date": "2023-10-30T10:41:52.000Z"
  },
  {
    "owner": "fen-lab",
    "repo": "fen-lab.github.io",
    "date": "2025-04-14T07:45:45.000Z"
  },
  {
    "owner": "Ivry-Lab",
    "repo": "ivry-lab.github.io",
    "date": "2025-04-03T19:41:41.000Z"
  },
  {
    "owner": "Equipe-Hydrodyn",
    "repo": "Equipe-Hydrodyn.github",
    "date": "2025-07-10T14:50:51.000Z"
  },
  {
    "owner": "in4lab",
    "repo": "in4lab.github.io",
    "date": "2025-04-29T08:50:40.000Z"
  },
  {
    "owner": "senekit",
    "repo": "test_lab",
    "date": "2025-02-08T19:06:39.000Z"
  },
  {
    "owner": "inha-cnlab",
    "repo": "lab-page-test",
    "date": "2023-11-21T05:35:20.000Z"
  },
  {
    "owner": "shainova",
    "repo": "lab_website",
    "date": "2023-11-29T16:48:03.000Z"
  },
  {
    "owner": "yuuwang0204",
    "repo": "Guo-Lab-Official",
    "date": "2023-09-25T21:23:58.000Z"
  },
  {
    "owner": "IDImmune",
    "repo": "ImmunRecog",
    "date": "2025-02-24T21:15:34.000Z"
  },
  {
    "owner": "mlcvlab-fasilkom-ui",
    "repo": "mlcvlab-fasilkom-ui.github.io",
    "date": "2021-08-14T20:46:21.000Z"
  },
  {
    "owner": "bhattacharya-a-bt",
    "repo": "bhattacharya-a-bt.github.io",
    "date": "2023-06-22T19:44:20.000Z"
  },
  {
    "owner": "HFXE",
    "repo": "HFXE-website",
    "date": "2024-11-15T17:59:51.000Z"
  },
  {
    "owner": "SCUT-ACIG",
    "repo": "DrQingLab",
    "date": "2025-05-27T09:26:47.000Z"
  },
  {
    "owner": "chienlab-bioic",
    "repo": "chienlab-bioic.github.io",
    "date": "2023-08-08T18:57:43.000Z"
  },
  {
    "owner": "mini-cornell",
    "repo": "mini-cornell.github.io",
    "date": "2024-01-31T23:41:34.000Z"
  },
  {
    "owner": "nsl-cmuq",
    "repo": "nsl-cmuq.github.io",
    "date": "2023-08-08T22:16:08.000Z"
  },
  {
    "owner": "ZMonfared",
    "repo": "DSAIlab",
    "date": "2024-10-29T11:50:03.000Z"
  },
  {
    "owner": "kruegert",
    "repo": "krueger-lab",
    "date": "2023-07-03T14:12:00.000Z"
  },
  {
    "owner": "kavisubashlab",
    "repo": "kavisubashlab-website",
    "date": "2025-02-28T02:26:00.000Z"
  },
  {
    "owner": "Willmund-lab",
    "repo": "willmund-lab.github.io",
    "date": "2024-11-05T18:34:38.000Z"
  },
  {
    "owner": "SMattevi",
    "repo": "CompuB-website",
    "date": "2025-05-23T11:45:41.000Z"
  },
  {
    "owner": "zeysun",
    "repo": "feng-lab",
    "date": "2025-05-30T19:05:14.000Z"
  },
  {
    "owner": "VIPL-VSU",
    "repo": "vipl-vsu.github.io",
    "date": "2025-07-21T08:54:16.000Z"
  },
  {
    "owner": "zjh2857",
    "repo": "lab-website",
    "date": "2024-11-16T01:12:25.000Z"
  },
  {
    "owner": "antonysuv",
    "repo": "suvorov_lab",
    "date": "2023-06-25T02:53:37.000Z"
  },
  {
    "owner": "NUS-LID",
    "repo": "NUS-LID.github.io",
    "date": "2023-06-07T01:56:34.000Z"
  },
  {
    "owner": "sarthakchandra94",
    "repo": "lab-website",
    "date": "2025-06-26T18:39:40.000Z"
  },
  {
    "owner": "elliott-lab",
    "repo": "elliott-lab.github.io",
    "date": "2025-05-06T17:33:09.000Z"
  },
  {
    "owner": "ICArmenian-Mycologists",
    "repo": "ICArmenian-Mycologists.github.io",
    "date": "2023-05-25T06:13:08.000Z"
  },
  {
    "owner": "LaBackDoor",
    "repo": "lab-website",
    "date": "2025-05-14T15:27:17.000Z"
  },
  {
    "owner": "kamranabdicse",
    "repo": "pars-lab",
    "date": "2025-02-23T12:52:44.000Z"
  },
  {
    "owner": "InSilicoVida",
    "repo": "InSilicoVida",
    "date": "2023-11-10T11:29:28.000Z"
  },
  {
    "owner": "NVL-Lab",
    "repo": "NVL-Lab.github.io",
    "date": "2023-04-21T17:55:52.000Z"
  },
  {
    "owner": "CreAI-Lab",
    "repo": "creai-lab.github.io",
    "date": "2025-04-24T15:12:26.000Z"
  },
  {
    "owner": "mshah9",
    "repo": "crossleylab-site",
    "date": "2024-03-29T06:38:41.000Z"
  },
  {
    "owner": "ByronChen12138",
    "repo": "AURORAE_Home",
    "date": "2025-03-27T17:02:54.000Z"
  },
  {
    "owner": "MLNTeam-Unical",
    "repo": "MLNTeam-Unical.github.io",
    "date": "2023-11-09T14:59:26.000Z"
  },
  {
    "owner": "GumusLab",
    "repo": "lab-website",
    "date": "2023-03-13T19:40:27.000Z"
  },
  {
    "owner": "PALM-Lab",
    "repo": "PALM-Lab.github.io",
    "date": "2023-12-17T04:21:43.000Z"
  },
  {
    "owner": "gary1003",
    "repo": "yt-lab-website",
    "date": "2025-03-06T05:44:07.000Z"
  },
  {
    "owner": "fangmengCQ",
    "repo": "raolab-site-preview",
    "date": "2024-12-20T16:32:08.000Z"
  },
  {
    "owner": "UA-MRI",
    "repo": "ua-mri.github.io",
    "date": "2025-01-21T22:11:12.000Z"
  },
  {
    "owner": "KCrane0817",
    "repo": "jhwang-webpage",
    "date": "2025-03-18T10:45:34.000Z"
  },
  {
    "owner": "QuantMarineEcoLab",
    "repo": "ires-marine-costarica",
    "date": "2023-10-22T18:47:32.000Z"
  },
  {
    "owner": "THUSIGSDRMLAB",
    "repo": "DRM-Lab-Website",
    "date": "2024-01-25T10:36:34.000Z"
  },
  {
    "owner": "AIMR-Lab",
    "repo": "website",
    "date": "2024-12-13T06:16:54.000Z"
  },
  {
    "owner": "Bestxixi",
    "repo": "test-lab-website",
    "date": "2024-12-22T08:42:30.000Z"
  },
  {
    "owner": "ianyang66",
    "repo": "NTU-STL-Website",
    "date": "2024-11-10T11:09:27.000Z"
  },
  {
    "owner": "M1andy",
    "repo": "Jia-Liu-Team",
    "date": "2025-04-21T09:06:40.000Z"
  },
  {
    "owner": "VPEC-Lab",
    "repo": "vpec-website",
    "date": "2024-01-12T04:18:57.000Z"
  },
  {
    "owner": "takushim",
    "repo": "takushim.github.io",
    "date": "2024-04-21T01:12:10.000Z"
  },
  {
    "owner": "portmajm",
    "repo": "julia-portmann",
    "date": "2025-03-12T19:18:58.000Z"
  },
  {
    "owner": "slash1028",
    "repo": "tdsv_dataset",
    "date": "2024-08-28T04:39:06.000Z"
  },
  {
    "owner": "WooHyuna",
    "repo": "nolabtest.github.io",
    "date": "2025-01-14T05:26:50.000Z"
  },
  {
    "owner": "sis-lab28",
    "repo": "nothing",
    "date": "2025-06-26T23:25:40.000Z"
  },
  {
    "owner": "SCAI-JHU",
    "repo": "SCAI-JHU.github.io",
    "date": "2024-06-09T17:41:15.000Z"
  },
  {
    "owner": "evomol-lab",
    "repo": "home",
    "date": "2024-02-25T14:12:37.000Z"
  },
  {
    "owner": "heliossun",
    "repo": "Tao-Lab-Website",
    "date": "2024-04-20T01:39:37.000Z"
  },
  {
    "owner": "WCU-AIR",
    "repo": "airlab",
    "date": "2025-05-30T13:55:31.000Z"
  },
  {
    "owner": "Yunqing-Yu",
    "repo": "yulab",
    "date": "2025-05-24T20:49:33.000Z"
  },
  {
    "owner": "Conorisco",
    "repo": "lab_website",
    "date": "2025-02-19T14:28:56.000Z"
  },
  {
    "owner": "markdne",
    "repo": "test-lab-website",
    "date": "2025-02-26T17:15:50.000Z"
  },
  {
    "owner": "holoviromic",
    "repo": "The-Little-Things",
    "date": "2025-05-28T11:00:31.000Z"
  },
  {
    "owner": "ivkarla",
    "repo": "principe-lab-website",
    "date": "2025-04-25T17:48:04.000Z"
  },
  {
    "owner": "IMASSP-TL",
    "repo": "imassp-tl.github.io",
    "date": "2023-09-21T14:30:21.000Z"
  },
  {
    "owner": "amkharazi",
    "repo": "temp-lab-repo",
    "date": "2024-12-07T09:43:47.000Z"
  },
  {
    "owner": "SalivaryCommunication",
    "repo": "Jasmer-Website-Template",
    "date": "2025-02-10T03:52:30.000Z"
  },
  {
    "owner": "Poh-BrainMemLab",
    "repo": "BrainMemLab",
    "date": "2025-01-21T01:46:34.000Z"
  },
  {
    "owner": "StrangerLab",
    "repo": "Stranger-Genomics-Lab",
    "date": "2024-07-25T02:14:03.000Z"
  },
  {
    "owner": "lu-jiayi",
    "repo": "seallab",
    "date": "2025-07-24T17:10:39.000Z"
  },
  {
    "owner": "kimberlymeier",
    "repo": "meierlab.github.io",
    "date": "2023-10-26T21:54:17.000Z"
  },
  {
    "owner": "Dichter-Jang",
    "repo": "cmclab",
    "date": "2025-07-18T13:13:18.000Z"
  },
  {
    "owner": "ENHANCELABNZ",
    "repo": "leasklab",
    "date": "2025-02-13T05:57:51.000Z"
  },
  {
    "owner": "abbastshaikh",
    "repo": "shaikh-lab-website",
    "date": "2023-06-01T02:11:39.000Z"
  },
  {
    "owner": "JfanLiu",
    "repo": "300-lab-website",
    "date": "2021-08-14T20:46:21.000Z"
  },
  {
    "owner": "mvaudel",
    "repo": "early_signs_lab",
    "date": "2025-05-22T20:09:52.000Z"
  },
  {
    "owner": "cjobara",
    "repo": "Obara-Lab-Website",
    "date": "2024-03-23T01:08:15.000Z"
  },
  {
    "owner": "bruntsch",
    "repo": "lonsdorflab-website",
    "date": "2025-02-11T14:38:25.000Z"
  },
  {
    "owner": "islandevolution",
    "repo": "islandevolution.github.io",
    "date": "2024-09-12T11:16:14.000Z"
  },
  {
    "owner": "InfoLab-SKKU",
    "repo": "infolab-skku.github.io",
    "date": "2021-08-14T20:46:21.000Z"
  },
  {
    "owner": "Drm23456",
    "repo": "DRM-Lab-Website",
    "date": "2024-01-24T08:32:35.000Z"
  },
  {
    "owner": "johnshorter",
    "repo": "Shorter_lab_website",
    "date": "2025-02-17T15:24:54.000Z"
  },
  {
    "owner": "falquaddoomi",
    "repo": "redesigned-lab-website",
    "date": "2023-02-25T16:21:55.000Z"
  },
  {
    "owner": "cgchrfchscyrh",
    "repo": "Test_Dream",
    "date": "2025-05-14T19:33:15.000Z"
  },
  {
    "owner": "Gidntsquia",
    "repo": "alFolio-Rezoom-site",
    "date": "2023-06-06T20:35:31.000Z"
  },
  {
    "owner": "hilder-vitor",
    "repo": "hello-world",
    "date": "2024-07-26T13:09:01.000Z"
  },
  {
    "owner": "AbdulkadirOzel",
    "repo": "github-page-baysanlab",
    "date": "2023-09-08T11:20:45.000Z"
  },
  {
    "owner": "XIYANG1018",
    "repo": "pain-lab-website",
    "date": "2024-01-18T23:49:01.000Z"
  },
  {
    "owner": "miekoyao",
    "repo": "history-of-insulin-project",
    "date": "2025-03-18T19:11:53.000Z"
  },
  {
    "owner": "drramki-chop",
    "repo": "rajagopalan-lab",
    "date": "2024-01-08T00:26:05.000Z"
  },
  {
    "owner": "Glenn032787",
    "repo": "steiflab.github.io",
    "date": "2024-03-13T17:35:44.000Z"
  },
  {
    "owner": "SunXiaoBo-Lab",
    "repo": "SunXiaoBo-Lab",
    "date": "2024-12-10T08:36:01.000Z"
  },
  {
    "owner": "RaphaelPile",
    "repo": "Vibration_LISPEN.github.io",
    "date": "2023-12-06T14:56:23.000Z"
  },
  {
    "owner": "tatz-murakami",
    "repo": "murakami-lab",
    "date": "2025-04-11T00:24:04.000Z"
  },
  {
    "owner": "emes-laboratory",
    "repo": "EMES-Laboratory",
    "date": "2025-07-09T18:16:15.000Z"
  },
  {
    "owner": "Human-Agent-Interaction",
    "repo": "HAI-website",
    "date": "2023-09-06T18:59:25.000Z"
  },
  {
    "owner": "AIML-K",
    "repo": "lab-website",
    "date": "2023-09-10T05:36:46.000Z"
  },
  {
    "owner": "Thaumiel-lbh",
    "repo": "lab-website",
    "date": "2024-11-19T12:16:53.000Z"
  },
  {
    "owner": "XinxingZhang-Lab",
    "repo": "ZhangLab",
    "date": "2025-01-13T20:20:52.000Z"
  },
  {
    "owner": "sweet-research-group",
    "repo": "sweet-research-group.github.io",
    "date": "2025-03-02T00:23:14.000Z"
  },
  {
    "owner": "Sachin-Gadani",
    "repo": "anrc-website",
    "date": "2025-03-20T20:09:56.000Z"
  },
  {
    "owner": "adconvertino",
    "repo": "stress-lab.github.io",
    "date": "2025-02-20T21:52:17.000Z"
  },
  {
    "owner": "tahazakir",
    "repo": "mn-lab-site-demo",
    "date": "2024-02-15T09:38:23.000Z"
  },
  {
    "owner": "bhe-aim-imt",
    "repo": "bhe-aim-imt.github.io",
    "date": "2025-01-03T07:36:36.000Z"
  },
  {
    "owner": "davidwcleary",
    "repo": "cleary-lab.github.io",
    "date": "2025-06-24T14:37:06.000Z"
  },
  {
    "owner": "AGR114molecularBreeding",
    "repo": "lab-website",
    "date": "2023-12-02T15:22:34.000Z"
  },
  {
    "owner": "DNAReplicationLab",
    "repo": "DNA-replication-group-website",
    "date": "2023-11-27T17:30:03.000Z"
  },
  {
    "owner": "Ecological-Complexity-Lab",
    "repo": "lab_website",
    "date": "2023-11-29T16:54:44.000Z"
  },
  {
    "owner": "AI3-GenAI4Sci",
    "repo": "lab-website",
    "date": "2024-11-20T04:03:52.000Z"
  },
  {
    "owner": "bhatnagararchit",
    "repo": "grill-lab-test-website",
    "date": "2023-04-25T02:45:55.000Z"
  },
  {
    "owner": "nan-dre",
    "repo": "ucs-lab",
    "date": "2023-11-02T11:45:27.000Z"
  },
  {
    "owner": "3DSIG-COSI",
    "repo": "new-website",
    "date": "2023-05-16T18:49:29.000Z"
  },
  {
    "owner": "zeyang-shen",
    "repo": "bioinfo-shen-lab",
    "date": "2025-07-15T02:03:10.000Z"
  },
  {
    "owner": "Prasad-adhi",
    "repo": "CVL-website",
    "date": "2025-02-01T13:04:41.000Z"
  },
  {
    "owner": "bhe-aim-ipbs",
    "repo": "bhe-aim-ipbs.github.io",
    "date": "2025-05-22T07:34:13.000Z"
  },
  {
    "owner": "Machado-Lab-UMD",
    "repo": "machado-lab-umd.github.io",
    "date": "2025-03-19T18:10:07.000Z"
  },
  {
    "owner": "daniel-ringis",
    "repo": "SigProc-Website",
    "date": "2021-08-14T20:46:21.000Z"
  },
  {
    "owner": "ELLIS-Unit-Graz",
    "repo": "ELLIS-Unit-Graz.github.io",
    "date": "2025-07-30T14:22:56.000Z"
  },
  {
    "owner": "QiMeng-Team",
    "repo": "QiMeng-Team",
    "date": "2025-02-17T06:39:41.000Z"
  },
  {
    "owner": "lilin-bme",
    "repo": "lilin-try",
    "date": "2023-09-28T09:44:12.000Z"
  },
  {
    "owner": "Goffaux-Lab",
    "repo": "goffaux-lab",
    "date": "2023-03-03T09:44:51.000Z"
  },
  {
    "owner": "carvalhoab",
    "repo": "renomica",
    "date": "2024-04-27T01:12:28.000Z"
  },
  {
    "owner": "mycroorg",
    "repo": "mycroorg.github.io",
    "date": "2024-09-25T13:49:15.000Z"
  },
  {
    "owner": "Sun-QP",
    "repo": "Jiaming-lab",
    "date": "2025-08-06T14:44:09.000Z"
  },
  {
    "owner": "ucf-draco-lab",
    "repo": "ucf-draco-lab-old-github.io",
    "date": "2023-06-08T14:46:07.000Z"
  },
  {
    "owner": "SKILL-Lab-Lehigh",
    "repo": "Website",
    "date": "2024-11-23T01:15:27.000Z"
  },
  {
    "owner": "stogunjo",
    "repo": "cmsp",
    "date": "2024-10-28T08:12:44.000Z"
  },
  {
    "owner": "RodolfoBaez",
    "repo": "ThinIceProject-RAB",
    "date": "2021-08-14T20:46:21.000Z"
  },
  {
    "owner": "hyxtj",
    "repo": "Tongji-Waste-Free.github.io",
    "date": "2025-03-13T13:34:36.000Z"
  },
  {
    "owner": "XinrunDu",
    "repo": "m-a-p_home_page",
    "date": "2024-03-06T06:42:19.000Z"
  },
  {
    "owner": "HITSZ-MAS",
    "repo": "mas-lab-website",
    "date": "2024-01-21T05:58:39.000Z"
  },
  {
    "owner": "lilin-bme",
    "repo": "lin-lab-sjtu",
    "date": "2023-09-03T09:31:35.000Z"
  },
  {
    "owner": "hyxtj",
    "repo": "tju-vex.github.io",
    "date": "2025-03-07T02:18:13.000Z"
  },
  {
    "owner": "NSFThinIce",
    "repo": "ThinIceProject",
    "date": "2021-08-14T20:46:21.000Z"
  },
  {
    "owner": "STAIR-BUPT",
    "repo": "STAIR-BUPT-Homepage",
    "date": "2024-03-28T06:23:17.000Z"
  },
  {
    "owner": "cgchrfchscyrh",
    "repo": "AIS-lab-website-main",
    "date": "2025-05-14T19:33:15.000Z"
  },
  {
    "owner": "Pengwei-Yang",
    "repo": "mig-lab-website",
    "date": "2025-07-14T01:30:53.000Z"
  },
  {
    "owner": "ZinanLin-Oscar",
    "repo": "sdu-smile-lab",
    "date": "2025-04-13T19:07:48.000Z"
  },
  {
    "owner": "norman-lab-msk",
    "repo": "norman-lab-website",
    "date": "2024-06-10T19:16:39.000Z"
  },
  {
    "owner": "acs-queens",
    "repo": "Q-ACS-Website",
    "date": "2023-10-18T21:53:10.000Z"
  },
  {
    "owner": "NeuroCognitiveImagingLab",
    "repo": "NCIL-website",
    "date": "2021-08-14T20:46:21.000Z"
  },
  {
    "owner": "integrativemicrobiomesciences-lab",
    "repo": "Monash-Microbiome-symposium2025",
    "date": "2025-03-24T06:50:40.000Z"
  },
  {
    "owner": "rebullm",
    "repo": "Bennett-Lab-website-v1.1",
    "date": "2023-04-24T18:28:27.000Z"
  },
  {
    "owner": "mpec-lab",
    "repo": "mpec-lab-website",
    "date": "2025-05-07T08:44:00.000Z"
  },
  {
    "owner": "Minee-Liane-Choi",
    "repo": "MineeChoiLab",
    "date": "2023-04-03T04:48:04.000Z"
  },
  {
    "owner": "zelezniak-lab",
    "repo": "synthbiolab.github.io",
    "date": "2023-10-25T12:32:19.000Z"
  },
  {
    "owner": "dustin-nguyen-qil",
    "repo": "QIL",
    "date": "2023-12-14T04:26:14.000Z"
  },
  {
    "owner": "sherry-home",
    "repo": "Mona-lab.github.io",
    "date": "2024-06-20T01:30:32.000Z"
  },
  {
    "owner": "Alexander-McGrath",
    "repo": "MEEM-Lab-Site",
    "date": "2023-05-05T01:55:57.000Z"
  },
  {
    "owner": "BU-Neuromics",
    "repo": "neuromics-lab-website",
    "date": "2024-09-09T14:42:29.000Z"
  },
  {
    "owner": "gmkov",
    "repo": "montejo-kovacevich-lab-website",
    "date": "2025-03-21T22:17:47.000Z"
  },
  {
    "owner": "bloch-elkouby-lab",
    "repo": "website",
    "date": "2023-11-19T17:49:48.000Z"
  },
  {
    "owner": "josephmluna",
    "repo": "LabWebsite",
    "date": "2024-06-24T17:14:25.000Z"
  },
  {
    "owner": "vonMentzer-Group",
    "repo": "vonMentzer-Group.github.io",
    "date": "2023-04-28T20:14:40.000Z"
  },
  {
    "owner": "ajschulz",
    "repo": "ajschulz_old.github.io",
    "date": "2024-04-20T00:54:36.000Z"
  },
  {
    "owner": "hyojin-park-neuro",
    "repo": "neureca",
    "date": "2023-04-20T17:40:25.000Z"
  },
  {
    "owner": "konigsbergi",
    "repo": "personal_website",
    "date": "2024-05-12T06:13:47.000Z"
  },
  {
    "owner": "Libbya-crick",
    "repo": "Libby-Lab-Website-2",
    "date": "2025-05-08T13:31:21.000Z"
  },
  {
    "owner": "mf1-btr",
    "repo": "mf1-btr.github.io",
    "date": "2024-02-22T20:23:25.000Z"
  },
  {
    "owner": "future-robotics-lab",
    "repo": "future-robotics-lab.github.io",
    "date": "2024-05-23T11:14:40.000Z"
  },
  {
    "owner": "LASCA-IC-UNICAMP",
    "repo": "lasca-website",
    "date": "2024-07-30T23:35:28.000Z"
  },
  {
    "owner": "unisg-ics-dsnlp",
    "repo": "ds-nlp-web",
    "date": "2025-05-22T20:58:51.000Z"
  },
  {
    "owner": "roberttwomey",
    "repo": "cohab-lab.net",
    "date": "2024-10-04T12:52:54.000Z"
  },
  {
    "owner": "trishullab",
    "repo": "trishullab.github.io",
    "date": "2024-07-18T11:55:54.000Z"
  },
  {
    "owner": "jfogrady1",
    "repo": "UCD-AGG-Website",
    "date": "2024-10-23T19:28:54.000Z"
  },
  {
    "owner": "WISCAD",
    "repo": "wiscad",
    "date": "2024-05-30T17:18:45.000Z"
  },
  {
    "owner": "nevaehRen",
    "repo": "nevaehRen.github.io",
    "date": "2024-04-26T00:04:47.000Z"
  },
  {
    "owner": "pengrui-rio",
    "repo": "pengrui-rio_flexcom.github.io",
    "date": "2025-01-30T06:11:16.000Z"
  },
  {
    "owner": "comp-cogneuro-lang",
    "repo": "ccnl",
    "date": "2024-09-10T13:28:27.000Z"
  },
  {
    "owner": "dea-pshk",
    "repo": "computational-radiation-biology-and-oncology",
    "date": "2024-12-04T11:40:03.000Z"
  },
  {
    "owner": "Saudi-Medical-AI-Lab",
    "repo": "website",
    "date": "2023-11-27T22:12:38.000Z"
  },
  {
    "owner": "gt-systems",
    "repo": "gt-systems.github.io",
    "date": "2024-03-10T04:08:06.000Z"
  },
  {
    "owner": "boom-lab",
    "repo": "boomlab-website",
    "date": "2023-07-10T20:04:28.000Z"
  },
  {
    "owner": "pili-lab-ub",
    "repo": "pili.lab.github.io",
    "date": "2025-03-02T14:05:47.000Z"
  },
  {
    "owner": "pkpare",
    "repo": "Parekh_lab_website",
    "date": "2024-06-12T22:35:40.000Z"
  },
  {
    "owner": "KarkeyOfficial",
    "repo": "science-website",
    "date": "2024-09-09T09:56:43.000Z"
  },
  {
    "owner": "ManskeLab",
    "repo": "ManskeLab.github.io",
    "date": "2024-06-09T22:23:06.000Z"
  },
  {
    "owner": "dmreslab",
    "repo": "DM-res-lab",
    "date": "2024-08-18T10:29:47.000Z"
  },
  {
    "owner": "marinopagan",
    "repo": "pagan_lab",
    "date": "2024-08-28T20:46:37.000Z"
  },
  {
    "owner": "LMC-Lab",
    "repo": "lmclab.com",
    "date": "2024-07-08T02:35:51.000Z"
  },
  {
    "owner": "imaei",
    "repo": "imaei.github.io",
    "date": "2024-07-30T11:24:12.000Z"
  },
  {
    "owner": "rui-hua-rh",
    "repo": "sweet-research-group.github.io",
    "date": "2025-03-01T23:50:07.000Z"
  },
  {
    "owner": "IDEMLab",
    "repo": "IDEMLab.github.io",
    "date": "2024-09-13T18:48:42.000Z"
  },
  {
    "owner": "Guha-Group",
    "repo": "phoqus-group-website",
    "date": "2024-09-06T16:27:10.000Z"
  },
  {
    "owner": "crossleylab",
    "repo": "crossleylab.github.io",
    "date": "2024-04-02T05:51:37.000Z"
  },
  {
    "owner": "steiflab",
    "repo": "steiflab.github.io",
    "date": "2024-07-29T16:45:26.000Z"
  },
  {
    "owner": "vuong-lab",
    "repo": "vuong-lab.github.io",
    "date": "2024-07-01T19:12:34.000Z"
  },
  {
    "owner": "ecotran",
    "repo": "ecotran.github.io",
    "date": "2024-08-18T22:53:25.000Z"
  },
  {
    "owner": "CalebAguayo",
    "repo": "McNuttLab",
    "date": "2024-06-06T20:10:13.000Z"
  },
  {
    "owner": "ZLWSSS",
    "repo": "my_test_labwebsite",
    "date": "2024-09-19T02:55:17.000Z"
  },
  {
    "owner": "Ambient-Intelligence-Lab-UMich-EECS",
    "repo": "ami_lab_website",
    "date": "2025-02-09T04:57:10.000Z"
  },
  {
    "owner": "INNVATION1",
    "repo": "INNVATION1.github.io",
    "date": "2024-05-29T13:08:20.000Z"
  },
  {
    "owner": "labberger",
    "repo": "labberger.github.io",
    "date": "2024-05-31T20:26:19.000Z"
  },
  {
    "owner": "ksabanlab",
    "repo": "ksabanlab.github.io",
    "date": "2024-06-22T12:10:50.000Z"
  },
  {
    "owner": "Electrogenomics-Group",
    "repo": "electrogenomics-group.github.io",
    "date": "2024-09-25T09:26:57.000Z"
  },
  {
    "owner": "68104426",
    "repo": "68104426.github.io",
    "date": "2024-09-10T08:13:22.000Z"
  },
  {
    "owner": "zhushiminlab",
    "repo": "zhushiminlab.github.io",
    "date": "2024-08-28T05:37:25.000Z"
  },
  {
    "owner": "pinglan753",
    "repo": "pinglan753.github.io",
    "date": "2024-09-14T13:34:42.000Z"
  },
  {
    "owner": "Alexander-McGrath",
    "repo": "AHMcGrath",
    "date": "2023-06-09T00:20:04.000Z"
  },
  {
    "owner": "MichaelXinyuanZhang",
    "repo": "MichaelXinyuanZhang.github.io",
    "date": "2024-04-23T04:13:26.000Z"
  },
  {
    "owner": "yvelasco",
    "repo": "testing3",
    "date": "2024-08-05T02:07:14.000Z"
  },
  {
    "owner": "balitimustapha",
    "repo": "metho-website",
    "date": "2024-10-11T07:45:45.000Z"
  },
  {
    "owner": "NJUSTzandyz",
    "repo": "cvlg",
    "date": "2024-07-16T12:30:40.000Z"
  },
  {
    "owner": "Sustainable-Energy-Storage-Recycling",
    "repo": "Sustainable-Energy-Storage-Recycling.github",
    "date": "2024-07-24T19:23:44.000Z"
  },
  {
    "owner": "calvinklai",
    "repo": "diversitysciencelab",
    "date": "2024-07-16T21:56:04.000Z"
  },
  {
    "owner": "mintbora",
    "repo": "gimlab",
    "date": "2024-09-02T11:21:44.000Z"
  },
  {
    "owner": "luckyzoxo",
    "repo": "TeamIntroduction",
    "date": "2024-07-22T08:31:05.000Z"
  },
  {
    "owner": "NeyhartLab",
    "repo": "NeyhartLabWebsite",
    "date": "2024-09-29T16:32:56.000Z"
  },
  {
    "owner": "dohuuphu",
    "repo": "ACM_NYCU",
    "date": "2024-12-03T05:52:22.000Z"
  },
  {
    "owner": "ZMonfared",
    "repo": "MOFAIlab",
    "date": "2024-10-17T09:21:49.000Z"
  },
  {
    "owner": "margoemont",
    "repo": "emontlab",
    "date": "2024-06-24T17:44:28.000Z"
  },
  {
    "owner": "kdr400219",
    "repo": "REDDYlab",
    "date": "2024-08-18T20:31:34.000Z"
  },
  {
    "owner": "yushi1898",
    "repo": "ShiLab",
    "date": "2024-08-29T15:47:34.000Z"
  },
  {
    "owner": "salmalis",
    "repo": "salmalis",
    "date": "2024-09-30T20:49:27.000Z"
  },
  {
    "owner": "miayan0110",
    "repo": "fudemosite",
    "date": "2024-09-03T08:38:52.000Z"
  },
  {
    "owner": "tianai321",
    "repo": "GIRT",
    "date": "2025-03-06T12:51:16.000Z"
  },
  {
    "owner": "dgtrung",
    "repo": "sleeptracking",
    "date": "2024-04-23T01:45:31.000Z"
  },
  {
    "owner": "cedricnp03",
    "repo": "sktlweb",
    "date": "2024-09-23T14:03:35.000Z"
  },
  {
    "owner": "mukhe027",
    "repo": "scubalab",
    "date": "2024-07-22T13:23:27.000Z"
  },
  {
    "owner": "jadebarclay",
    "repo": "nmsk",
    "date": "2024-04-02T03:11:39.000Z"
  },
  {
    "owner": "daimabiabia",
    "repo": "zhandui",
    "date": "2025-05-03T03:23:02.000Z"
  },
  {
    "owner": "ADMIS-TONGJI",
    "repo": "ADMIS-TONGJI.github.io",
    "date": "2024-10-07T06:31:11.000Z"
  },
  {
    "owner": "ghhlab",
    "repo": "globalhealthandhazardslab",
    "date": "2024-09-20T18:27:10.000Z"
  },
  {
    "owner": "ChengroupSJTU",
    "repo": "Homepage",
    "date": "2024-06-21T05:28:06.000Z"
  },
  {
    "owner": "zzi4",
    "repo": "zzi4",
    "date": "2024-07-24T11:26:19.000Z"
  },
  {
    "owner": "cgenomicslab",
    "repo": "cgenomicslab_green",
    "date": "2024-07-08T19:54:50.000Z"
  },
  {
    "owner": "OpenAGCI",
    "repo": "openagci-website",
    "date": "2025-02-24T02:51:06.000Z"
  },
  {
    "owner": "sbx126",
    "repo": "ml-website",
    "date": "2024-07-10T06:38:33.000Z"
  },
  {
    "owner": "SDML-KU",
    "repo": "sdml-ku.github.io",
    "date": "2024-02-02T08:43:33.000Z"
  },
  {
    "owner": "samanjoy2",
    "repo": "saman-lab",
    "date": "2024-09-25T20:10:06.000Z"
  },
  {
    "owner": "199248",
    "repo": "BOF_website",
    "date": "2025-03-09T09:18:35.000Z"
  },
  {
    "owner": "rosenbergerkm",
    "repo": "rosenbergerkm.github.io",
    "date": "2024-04-04T18:45:26.000Z"
  },
  {
    "owner": "woquchonglang",
    "repo": "SCNU_PIONEER",
    "date": "2025-03-12T11:50:24.000Z"
  },
  {
    "owner": "zplszz",
    "repo": "WMJ_website",
    "date": "2025-03-28T14:06:45.000Z"
  },
  {
    "owner": "nickader",
    "repo": "AderLabWebsite",
    "date": "2024-04-18T15:46:05.000Z"
  },
  {
    "owner": "JayakrishnanAjayakumar",
    "repo": "ghhlab-website",
    "date": "2024-09-20T15:36:46.000Z"
  },
  {
    "owner": "direwuff",
    "repo": "Bad-DNA",
    "date": "2024-09-23T13:34:28.000Z"
  },
  {
    "owner": "Imaging-AI-for-Health-virtual-lab",
    "repo": "ai4med",
    "date": "2023-04-20T11:52:16.000Z"
  },
  {
    "owner": "gszh",
    "repo": "lab-website",
    "date": "2024-10-17T10:23:02.000Z"
  },
  {
    "owner": "QLYHY",
    "repo": "HUE_Smartcars",
    "date": "2025-04-02T08:58:19.000Z"
  },
  {
    "owner": "ipoom-jeong",
    "repo": "gaudi-lab",
    "date": "2024-07-18T12:55:30.000Z"
  },
  {
    "owner": "paperhow04177",
    "repo": "DX_webside",
    "date": "2025-03-07T13:48:02.000Z"
  },
  {
    "owner": "Author72",
    "repo": "SUSTechRC_Website",
    "date": "2025-03-25T14:41:16.000Z"
  },
  {
    "owner": "Ding-Group",
    "repo": "Ding-Group.github.io",
    "date": "2024-04-09T22:52:38.000Z"
  },
  {
    "owner": "duotry",
    "repo": "hongying_website",
    "date": "2025-03-28T14:19:35.000Z"
  },
  {
    "owner": "Axiaopei",
    "repo": "Taurus_website",
    "date": "2025-03-28T08:35:21.000Z"
  },
  {
    "owner": "redhorn144",
    "repo": "Alex-Shaffer",
    "date": "2024-05-30T05:33:25.000Z"
  },
  {
    "owner": "andayao",
    "repo": "xinyue_website",
    "date": "2025-03-28T10:50:47.000Z"
  },
  {
    "owner": "muzier9",
    "repo": "Tkatchenko-OuJiangLab-Website",
    "date": "2024-08-23T09:05:35.000Z"
  },
  {
    "owner": "BCCHVisionLab",
    "repo": "testingtesting.github.io",
    "date": "2024-10-10T20:59:06.000Z"
  },
  {
    "owner": "AzirRex",
    "repo": "Tongji-AIAO-Lab",
    "date": "2024-07-16T12:16:13.000Z"
  },
  {
    "owner": "Tonywang2004",
    "repo": "test-tju-2252948",
    "date": "2024-07-22T09:16:34.000Z"
  },
  {
    "owner": "twpqeqr123",
    "repo": "Dynamic-X-website",
    "date": "2025-03-13T13:30:00.000Z"
  },
  {
    "owner": "gvinodkg",
    "repo": "your-lab-website",
    "date": "2025-03-19T18:26:22.000Z"
  },
  {
    "owner": "estu-mlcv",
    "repo": "website",
    "date": "2024-09-12T17:37:19.000Z"
  },
  {
    "owner": "tiansheng-zhu",
    "repo": "demo",
    "date": "2024-07-17T12:44:13.000Z"
  },
  {
    "owner": "Yby-yxf",
    "repo": "Best",
    "date": "2025-03-11T11:21:06.000Z"
  },
  {
    "owner": "JOKER301557",
    "repo": "SeekerRM-Seeker_website",
    "date": "2025-03-25T00:38:20.000Z"
  },
  {
    "owner": "craithel",
    "repo": "cr-website-template",
    "date": "2021-08-14T20:46:21.000Z"
  },
  {
    "owner": "daxdelvira",
    "repo": "daxdelvira.github.io",
    "date": "2024-09-25T12:25:38.000Z"
  },
  {
    "owner": "pooja-zen",
    "repo": "scremaschigroup",
    "date": "2024-05-02T20:49:27.000Z"
  },
  {
    "owner": "nevercodecorrect",
    "repo": "lab-website-cispa",
    "date": "2024-07-29T12:52:58.000Z"
  },
  {
    "owner": "sterding",
    "repo": "donglab.org",
    "date": "2023-10-19T02:26:01.000Z"
  },
  {
    "owner": "phipsonlab",
    "repo": "phipson-lab-website",
    "date": "2024-09-12T01:49:10.000Z"
  },
  {
    "owner": "gg2x-1",
    "repo": "VinciRobot",
    "date": "2025-08-08T08:45:52.000Z"
  },
  {
    "owner": "lizhouyu",
    "repo": "lab-website",
    "date": "2023-07-06T10:35:10.000Z"
  },
  {
    "owner": "spiderman-666",
    "repo": "new-project",
    "date": "2024-07-22T08:03:29.000Z"
  },
  {
    "owner": "Guaaaava",
    "repo": "tongji-lab-homepage-repo",
    "date": "2024-07-21T10:18:17.000Z"
  },
  {
    "owner": "XH-1365",
    "repo": "inventor_wedsite",
    "date": "2025-03-11T14:19:36.000Z"
  },
  {
    "owner": "changfengpro",
    "repo": "hy_website",
    "date": "2025-03-26T16:12:55.000Z"
  },
  {
    "owner": "engelhard-lab",
    "repo": "engelhard-lab",
    "date": "2024-09-21T20:59:14.000Z"
  },
  {
    "owner": "AIMV-handong",
    "repo": "AIMV-Lab",
    "date": "2024-07-01T21:09:04.000Z"
  },
  {
    "owner": "sbbe2024",
    "repo": "sbbe2024.github.io_KILL",
    "date": "2024-04-05T23:12:13.000Z"
  },
  {
    "owner": "saugatbh",
    "repo": "isrc-cnn.github.io",
    "date": "2024-10-18T13:50:22.000Z"
  },
  {
    "owner": "Hahn-Nehsoail",
    "repo": "DreamChaser_website",
    "date": "2025-03-11T09:01:53.000Z"
  },
  {
    "owner": "darkcome6",
    "repo": "SPR_website_1.0",
    "date": "2025-06-25T05:16:52.000Z"
  },
  {
    "owner": "WINK-YING",
    "repo": "IMCA_website",
    "date": "2025-03-27T14:09:27.000Z"
  },
  {
    "owner": "Holo-Spice",
    "repo": "wdr_website",
    "date": "2025-03-28T15:08:20.000Z"
  },
  {
    "owner": "Yn-life",
    "repo": "GIRT_website",
    "date": "2025-04-08T15:16:13.000Z"
  },
  {
    "owner": "Leandro-Iglesias",
    "repo": "Site-Teste",
    "date": "2024-10-08T18:50:44.000Z"
  },
  {
    "owner": "Mounika-analyst",
    "repo": "lab-website",
    "date": "2025-03-19T19:16:02.000Z"
  },
  {
    "owner": "HY-SL",
    "repo": "Test_Web",
    "date": "2025-03-11T08:13:03.000Z"
  },
  {
    "owner": "Bio-Mas-Lab",
    "repo": "LabWebsite",
    "date": "2024-09-05T16:26:12.000Z"
  },
  {
    "owner": "BriSky-2021",
    "repo": "MAIL-TALL-LAB",
    "date": "2024-08-29T05:06:40.000Z"
  },
  {
    "owner": "Muthu-Jeyanthi",
    "repo": "c3n_lab_temp",
    "date": "2024-07-14T09:43:13.000Z"
  },
  {
    "owner": "niko-long",
    "repo": "oxycat-lab-website",
    "date": "2024-10-12T14:12:44.000Z"
  },
  {
    "owner": "NextGen-Embodied-AI-Solutions-Lab",
    "repo": "NextGen-Embodied-AI-Solutions-Lab-Website",
    "date": "2025-02-13T02:11:09.000Z"
  },
  {
    "owner": "Bio-MingChen",
    "repo": "lab-website-demo",
    "date": "2024-07-05T07:46:44.000Z"
  },
  {
    "owner": "ACLab-Bioinfo",
    "repo": "aclab_website_1.1.5",
    "date": "2023-06-09T05:57:05.000Z"
  },
  {
    "owner": "GichanLee",
    "repo": "hanyang-selab",
    "date": "2025-01-06T06:38:45.000Z"
  },
  {
    "owner": "ewald-lab",
    "repo": "ewald-lab-website",
    "date": "2024-11-09T16:12:23.000Z"
  },
  {
    "owner": "venorthcarolina",
    "repo": "violets-website",
    "date": "2024-07-04T01:45:00.000Z"
  },
  {
    "owner": "fengxiaot",
    "repo": "sustechti",
    "date": "2024-03-28T03:18:23.000Z"
  },
  {
    "owner": "Combrink-Lab",
    "repo": "combrink-lab.github.io",
    "date": "2023-08-28T20:43:54.000Z"
  },
  {
    "owner": "mathis-group",
    "repo": "mathis-group.github.io",
    "date": "2024-06-24T17:30:42.000Z"
  },
  {
    "owner": "emhaynes",
    "repo": "hayneslab",
    "date": "2024-04-16T15:23:03.000Z"
  },
  {
    "owner": "iqr-lab",
    "repo": "iqr-lab.github.io",
    "date": "2023-11-27T20:57:25.000Z"
  },
  {
    "owner": "clareaulab",
    "repo": "clareau-lab-website",
    "date": "2025-02-22T14:04:15.000Z"
  },
  {
    "owner": "buviar",
    "repo": "buviar.github.io",
    "date": "2022-12-25T19:06:15.000Z"
  },
  {
    "owner": "vis-image-management",
    "repo": "vim-web",
    "date": "2023-07-12T13:11:23.000Z"
  },
  {
    "owner": "Meshinchi-Lab",
    "repo": "meshinchi-lab.github.io",
    "date": "2024-03-11T19:37:13.000Z"
  },
  {
    "owner": "kaifuchenlab",
    "repo": "kaifuchenlab.github.io",
    "date": "2023-01-20T17:29:34.000Z"
  },
  {
    "owner": "SysML-Princeton",
    "repo": "website_old",
    "date": "2025-01-27T22:32:43.000Z"
  },
  {
    "owner": "ellenbuckley",
    "repo": "ellenbuckley.github.io",
    "date": "2024-07-11T20:09:23.000Z"
  },
  {
    "owner": "jitinb",
    "repo": "scl",
    "date": "2024-06-06T20:07:50.000Z"
  },
  {
    "owner": "ipl-lab",
    "repo": "ipl-lab.github.io",
    "date": "2024-04-18T22:19:21.000Z"
  },
  {
    "owner": "scl-lab-iisc",
    "repo": "scl-lab-iisc.github.io",
    "date": "2024-06-02T10:18:40.000Z"
  },
  {
    "owner": "ajbaird",
    "repo": "LabWebsite",
    "date": "2023-08-20T22:11:17.000Z"
  },
  {
    "owner": "Climate-Data-Dynamics",
    "repo": "climate-data-dynamics.github.io",
    "date": "2021-08-14T20:46:21.000Z"
  },
  {
    "owner": "skandaarvind",
    "repo": "srilab",
    "date": "2023-07-16T00:53:41.000Z"
  },
  {
    "owner": "bvoightlab",
    "repo": "bvoightlab.github.io",
    "date": "2024-01-05T18:32:53.000Z"
  },
  {
    "owner": "Alexander-McGrath",
    "repo": "A_H_McGrath",
    "date": "2024-05-24T12:34:03.000Z"
  },
  {
    "owner": "sousagroup",
    "repo": "sousagroup.github.io",
    "date": "2023-08-23T16:14:41.000Z"
  },
  {
    "owner": "ubcrcc",
    "repo": "LWT-website",
    "date": "2024-10-31T18:43:02.000Z"
  },
  {
    "owner": "YoungXinyu1802",
    "repo": "labweb",
    "date": "2025-01-06T08:13:22.000Z"
  }
]